{
    "bootloader": "qmk-dfu",
    "ws2812": {
        "pin": "F1"
    },
    "encoder": {
        "rotary": [
            {"pin_a": "D5", "pin_b": "C7"}
        ]
    },
    "build": {
        "lto": true
    },
    "features": {
        "audio": false,
        "bootmagic": true,
        "encoder": true,
        "extrakey": true,
        "mousekey": true,
        "nkro": false,
        "rgb_matrix": true,
    },
    "matrix_pins": {
        "cols": ["B6", "B2", "B3", "B1", "F7", "F6", "F5", "F4"],
        "rows": ["D3", "D2", "D1", "D0", "B5", "B4", "E6", "D7", "C6", "D4"]
    }
}
