{
  "name": "Keyball46_Left",
  "vendorId": "0x5957",
  "productId": "0x0002",
  "lighting": "qmk_rgblight",
  "matrix": { "rows": 8, "cols": 6 },
  "layouts": {
    "keymap": [
      [{"y":1,"x":2},"0,2",{"x":9.75},"4,2"],
      [{"y":-0.87,"x":1},"0,1",{"x":1},"0,3",{"x":7.75},"4,3",{"x":1},"4,1"],
      [{"y":-0.88,"x":4},"0,4","0,5",{"x":3.75,"c":"#aaaaaa","h":1.5},"4,5",{"c":"#cccccc"},"4,4"],
      [{"y":-0.87},"0,0",{"x":13.75},"4,0"],
      [{"y":-0.38,"x":2},"1,2",{"x":9.75},"5,2"],
      [{"y":-0.87,"x":1},"1,1",{"x":1},"1,3",{"x":7.75},"5,3",{"x":1},"5,1"],
      [{"y":-0.88,"x":4},"1,4","1,5",{"x":0.25,"c":"#aaaaaa"},"3,5",{"x":1.25},"6,5",{"x":1.25,"c":"#cccccc"},"5,4"],
      [{"y":-0.87},"1,0",{"x":13.75},"5,0"],
      [{"y":-0.63,"x":9.75,"c":"#aaaaaa","h":1.5},"5,5"],
      [{"y":-0.75,"x":2,"c":"#cccccc"},"2,2",{"x":9.75},"6,2"],
      [{"y":-0.87,"x":1},"2,1",{"x":1},"2,3",{"x":7.75},"6,3",{"x":1},"6,1"],
      [{"y":-0.88,"x":4},"2,4","2,5",{"x":4.75},"6,4"],
      [{"y":-0.87},"2,0",{"x":13.75},"6,0"],
      [{"y":-0.38,"x":2},"3,2"],
      [{"y":-0.87,"x":1},"3,1",{"x":11.75},"7,1"],
      [{"y":-0.75},"3,0",{"x":13.75},"7,0"],
      [{"y":-0.88,"x":3.5,"c":"#aaaaaa"},"3,3",{"x":7.75},"7,2"],
      [{"r":10,"rx":6.5,"ry":4.25,"y":0.55,"x":-1.65},"3,4"],
      [{"r":-30,"rx":13,"y":-1.05,"x":-4.45,"h":1.25},"7,5"],
      [{"r":-20,"y":-0.2,"x":-3.3},"7,4"],
      [{"r":-10,"rx":0,"ry":0,"y":6.55,"x":10},"7,3"]
    ]
  }
}
