{
    "keyboard_name": "Stream Cheap 2x5",
    "url": "https://www.thingiverse.com/thing:4497991",
    "maintainer": "qmk",
    "width": 5,
    "height": 2,
    "layouts": {
        "LAYOUT_ortho_2x5": {
            "layout": [
                {"label":"K00", "x":0, "y":0},
                {"label":"K01", "x":1, "y":0},
                {"label":"K02", "x":2, "y":0},
                {"label":"K03", "x":3, "y":0},
                {"label":"K04", "x":4, "y":0},
                {"label":"K10", "x":0, "y":1},
                {"label":"K11", "x":1, "y":1},
                {"label":"K12", "x":2, "y":1},
                {"label":"K13", "x":3, "y":1},
                {"label":"K14", "x":4, "y":1}
            ]
        }
    }
}
