{
  "keyboard_name": "JJ50",
  "url": "",
  "maintainer": "qmk",
  "layouts": {
    "LAYOUT_ortho_5x12": {
      "layout": [{"label":"K011", "x":0, "y":0}, {"label":"K010", "x":1, "y":0}, {"label":"K009", "x":2, "y":0}, {"label":"K008", "x":3, "y":0}, {"label":"K004", "x":4, "y":0}, {"label":"K005", "x":5, "y":0}, {"label":"K006", "x":6, "y":0}, {"label":"K007", "x":7, "y":0}, {"label":"K003", "x":8, "y":0}, {"label":"K002", "x":9, "y":0}, {"label":"K201", "x":10, "y":0}, {"label":"K000", "x":11, "y":0}, {"label":"K111", "x":0, "y":1}, {"label":"K110", "x":1, "y":1}, {"label":"K109", "x":2, "y":1}, {"label":"K108", "x":3, "y":1}, {"label":"K104", "x":4, "y":1}, {"label":"K105", "x":5, "y":1}, {"label":"K106", "x":6, "y":1}, {"label":"K107", "x":7, "y":1}, {"label":"K103", "x":8, "y":1}, {"label":"K102", "x":9, "y":1}, {"label":"K001", "x":10, "y":1}, {"label":"K100", "x":11, "y":1}, {"label":"K211", "x":0, "y":2}, {"label":"K210", "x":1, "y":2}, {"label":"K209", "x":2, "y":2}, {"label":"K208", "x":3, "y":2}, {"label":"K204", "x":4, "y":2}, {"label":"K205", "x":5, "y":2}, {"label":"K206", "x":6, "y":2}, {"label":"K207", "x":7, "y":2}, {"label":"K203", "x":8, "y":2}, {"label":"K202", "x":9, "y":2}, {"label":"K101", "x":10, "y":2}, {"label":"K200", "x":11, "y":2}, {"label":"K311", "x":0, "y":3}, {"label":"K310", "x":1, "y":3}, {"label":"K309", "x":2, "y":3}, {"label":"K308", "x":3, "y":3}, {"label":"K304", "x":4, "y":3}, {"label":"K305", "x":5, "y":3}, {"label":"K306", "x":6, "y":3}, {"label":"K307", "x":7, "y":3}, {"label":"K303", "x":8, "y":3}, {"label":"K302", "x":9, "y":3}, {"label":"K301", "x":10, "y":3}, {"label":"K300", "x":11, "y":3}, {"label":"K411", "x":0, "y":4}, {"label":"K410", "x":1, "y":4}, {"label":"K409", "x":2, "y":4}, {"label":"K408", "x":3, "y":4}, {"label":"K404", "x":4, "y":4}, {"label":"K405", "x":5, "y":4}, {"label":"K406", "x":6, "y":4}, {"label":"K407", "x":7, "y":4}, {"label":"K403", "x":8, "y":4}, {"label":"K402", "x":9, "y":4}, {"label":"K401", "x":10, "y":4}, {"label":"K400", "x":11, "y":4}]
    }
  }
}
