{
    "manufacturer": "Isaac Rex",
    "keyboard_name": "Nifty Numpad",
    "url": "https://gitlab.com/Acliad/nifty-numpad",
    "maintainer": "Acliad",
    "processor": "RP2040",
    "bootloader": "rp2040",
    "features": {
        "bootmagic": true,
        "command": false,
        "console": false,
        "extrakey": true,
        "mousekey": true,
        "nkro": true,
        "rgb_matrix": true
    },
    "diode_direction": "ROW2COL",
    "matrix_pins": {
        "cols": ["GP17", "GP18", "GP15", "GP13", "GP14", "GP12"],
        "rows": ["GP20", "GP21", "GP22", "GP23", "GP24", "GP25"]
    },
    "usb": {
        "device_version": "1.0.0",
        "pid": "0x0000",
        "vid": "0x4E4E"
    },
    "ws2812": {
        "driver": "vendor",
        "pin": "GP19"
    },
    "rgb_matrix": {
        "driver": "ws2812",
        "animations": {
            "alpha_mods": true,
            "gradient_up_down": true,
            "breathing": true,
            "band_sat": true,
            "band_val": true,
            "band_pinwheel_sat": true,
            "band_pinwheel_val": true,
            "band_spiral_sat": true,
            "band_spiral_val": true,
            "cycle_all": true,
            "cycle_left_right": true,
            "cycle_up_down": true,
            "cycle_out_in": true,
            "cycle_out_in_dual": true,
            "rainbow_moving_chevron": true,
            "cycle_pinwheel": true,
            "cycle_spiral": true,
            "dual_beacon": true,
            "rainbow_beacon": true,
            "rainbow_pinwheels": true,
            "raindrops": true,
            "jellybean_raindrops": true,
            "typing_heatmap": true,
            "digital_rain": true,
            "solid_reactive_simple": true,
            "solid_reactive": true,
            "solid_reactive_wide": true,
            "solid_reactive_multiwide": true,
            "solid_reactive_cross": true,
            "solid_reactive_multicross": true,
            "solid_reactive_nexus": true,
            "solid_reactive_multinexus": true,
            "splash": true,
            "multisplash": true,
            "solid_splash": true,
            "solid_multisplash": true
        },
        "layout": [
            {"matrix": [0, 0], "x": 0,   "y": 0, "flags": 0},
            {"matrix": [0, 1], "x": 43,  "y": 0, "flags": 0},
            {"matrix": [0, 2], "x": 96,  "y": 0, "flags": 0},
            {"matrix": [0, 3], "x": 139, "y": 0, "flags": 0},
            {"matrix": [0, 4], "x": 181, "y": 0, "flags": 0},
            {"matrix": [0, 5], "x": 224, "y": 0, "flags": 0},
            {"matrix": [1, 0], "x": 0,   "y": 17, "flags": 0},
            {"matrix": [1, 1], "x": 43,  "y": 17, "flags": 0},
            {"matrix": [1, 2], "x": 96,  "y": 17, "flags": 0},
            {"matrix": [1, 3], "x": 139, "y": 17, "flags": 0},
            {"matrix": [1, 4], "x": 181, "y": 17, "flags": 0},
            {"matrix": [1, 5], "x": 224, "y": 17, "flags": 0},
            {"matrix": [2, 0], "x": 0,   "y": 29, "flags": 0},
            {"matrix": [2, 1], "x": 43,  "y": 29, "flags": 0},
            {"matrix": [2, 2], "x": 96,  "y": 29, "flags": 0},
            {"matrix": [2, 3], "x": 139, "y": 29, "flags": 0},
            {"matrix": [2, 4], "x": 181, "y": 29, "flags": 0},
            {"matrix": [2, 5], "x": 224, "y": 35, "flags": 0},
            {"matrix": [3, 0], "x": 0,   "y": 41, "flags": 0},
            {"matrix": [3, 1], "x": 43,  "y": 41, "flags": 0},
            {"matrix": [3, 2], "x": 96,  "y": 41, "flags": 0},
            {"matrix": [3, 3], "x": 139, "y": 41, "flags": 0},
            {"matrix": [3, 4], "x": 181, "y": 41, "flags": 0},
            {"matrix": [4, 0], "x": 0,   "y": 52, "flags": 0},
            {"matrix": [4, 1], "x": 43,  "y": 52, "flags": 0},
            {"matrix": [4, 2], "x": 96,  "y": 52, "flags": 0},
            {"matrix": [4, 3], "x": 139, "y": 52, "flags": 0},
            {"matrix": [4, 4], "x": 181, "y": 52, "flags": 0},
            {"matrix": [4, 5], "x": 224, "y": 58, "flags": 0},
            {"matrix": [5, 0], "x": 0,   "y": 64, "flags": 0},
            {"matrix": [5, 1], "x": 43,  "y": 64, "flags": 0},
            {"matrix": [5, 2], "x": 117, "y": 64, "flags": 0},
            {"matrix": [5, 3], "x": 181, "y": 64, "flags": 0}
        ]
    },
    "layouts": {
        "LAYOUT_numpad_6x6": {
            "layout": [
                {"matrix": [0, 0], "label": "F13", "x": 0, "y": 0},
                {"matrix": [0, 1], "label": "F19", "x": 1, "y": 0},
                {"matrix": [0, 2], "label": "BACKSPACE", "x": 2.25, "y": 0},
                {"matrix": [0, 3], "label": "TASK VIEW", "x": 3.25, "y": 0},
                {"matrix": [0, 4], "label": "EXPLORER", "x": 4.25, "y": 0},
                {"matrix": [0, 5], "label": "SCREENSHOT", "x": 5.25, "y": 0},
                
                {"matrix": [1, 0], "label": "F14", "x": 0, "y": 1.5},
                {"matrix": [1, 1], "label": "F20", "x": 1, "y": 1.5},
                {"matrix": [1, 2], "label": "NUM LOCK", "x": 2.25, "y": 1.5},
                {"matrix": [1, 3], "label": "/", "x": 3.25, "y": 1.5},
                {"matrix": [1, 4], "label": "*", "x": 4.25, "y": 1.5},
                {"matrix": [1, 5], "label": "-", "x": 5.25, "y": 1.5},

                {"matrix": [2, 0], "label": "F15", "x": 0, "y": 2.5},
                {"matrix": [2, 1], "label": "F21", "x": 1, "y": 2.5},
                {"matrix": [2, 2], "label": "7", "x": 2.25, "y": 2.5},
                {"matrix": [2, 3], "label": "8", "x": 3.25, "y": 2.5},
                {"matrix": [2, 4], "label": "9", "x": 4.25, "y": 2.5},
                {"matrix": [2, 5], "label": "+", "x": 5.25, "y": 2.5, "h": 2},

                {"matrix": [3, 0], "label": "F16", "x": 0, "y": 3.5},
                {"matrix": [3, 1], "label": "F22", "x": 1, "y": 3.5},
                {"matrix": [3, 2], "label": "4", "x": 2.25, "y": 3.5},
                {"matrix": [3, 3], "label": "5", "x": 3.25, "y": 3.5},
                {"matrix": [3, 4], "label": "6", "x": 4.25, "y": 3.5},

                {"matrix": [4, 0], "label": "F17", "x": 0, "y": 4.5},
                {"matrix": [4, 1], "label": "F23", "x": 1, "y": 4.5},
                {"matrix": [4, 2], "label": "1", "x": 2.25, "y": 4.5},
                {"matrix": [4, 3], "label": "2", "x": 3.25, "y": 4.5},
                {"matrix": [4, 4], "label": "3", "x": 4.25, "y": 4.5},
                {"matrix": [4, 5], "label": "ENTER", "x": 5.25, "y": 4.5, "h": 2},
                
                {"matrix": [5, 0], "label": "F18", "x": 0, "y": 5.5},
                {"matrix": [5, 1], "label": "F24", "x": 1, "y": 5.5},
                {"matrix": [5, 3], "label": "0", "x": 2.25, "y": 5.5, "w": 2},
                {"matrix": [5, 4], "label": ".", "x": 4.25, "y": 5.5}
            ]
        }
    }
}