{
    "keyboard_name": "Zeus",
    "manufacturer": "Koobaczech",
    "url": "",
    "maintainer": "Koobaczech",
    "usb": {
        "vid": "0x6963",
        "pid": "0x6966",
        "device_version": "0.0.1"
    },
    "matrix_pins": {
        "cols": ["F1", "F2", "F3", "F4", "F5", "F6", "F7", "A0", "A1", "A2", "A3", "A4", "A5", "A6", "A7", "C7", "C2", "C0"],
        "rows": ["F0", "C1", "E1", "E0", "D7", "D6"]
    },
    "diode_direction": "COL2ROW",
    "encoder": {
        "rotary": [
            {"pin_a": "E7", "pin_b": "E6", "resolution": 1}
        ]
    },
    "indicators": {
        "caps_lock": "C5",
        "num_lock": "C4",
        "scroll_lock": "C3",
        "on_state": 0
    },
    "rgblight": {
        "saturation_steps": 8,
        "brightness_steps": 8,
        "led_count": 2,
        "sleep": true,
        "animations": {
            "breathing": true,
            "rainbow_mood": true,
            "rainbow_swirl": true,
            "snake": true,
            "knight": true,
            "christmas": true,
            "static_gradient": true,
            "alternating": true,
            "twinkle": true
        }
    },
    "ws2812": {
        "pin": "D5"
    },
    "processor": "at90usb1286",
    "bootloader": "atmel-dfu",
    "layouts": {
        "LAYOUT_all": {
            "layout": [
                {"label": "Play/Pause", "matrix": [4, 15], "x": 3, "y": 0},

                {"label": "Esc", "matrix": [0, 0], "x": 0, "y": 1.5},

                {"label": "F1", "matrix": [0, 1], "x": 2, "y": 1.5},
                {"label": "F2", "matrix": [0, 2], "x": 3, "y": 1.5},
                {"label": "F3", "matrix": [0, 3], "x": 4, "y": 1.5},
                {"label": "F4", "matrix": [0, 4], "x": 5, "y": 1.5},

                {"label": "F5", "matrix": [0, 5], "x": 6.5, "y": 1.5},
                {"label": "F6", "matrix": [0, 6], "x": 7.5, "y": 1.5},
                {"label": "F7", "matrix": [0, 7], "x": 8.5, "y": 1.5},
                {"label": "F8", "matrix": [0, 8], "x": 9.5, "y": 1.5},

                {"label": "F9", "matrix": [0, 9], "x": 11, "y": 1.5},
                {"label": "F10", "matrix": [0, 10], "x": 12, "y": 1.5},
                {"label": "F11", "matrix": [0, 11], "x": 13, "y": 1.5},
                {"label": "F12", "matrix": [0, 12], "x": 14, "y": 1.5},

                {"label": "`", "matrix": [1, 0], "x": 0, "y": 2.75},
                {"label": "1", "matrix": [1, 1], "x": 1, "y": 2.75},
                {"label": "2", "matrix": [1, 2], "x": 2, "y": 2.75},
                {"label": "3", "matrix": [1, 3], "x": 3, "y": 2.75},
                {"label": "4", "matrix": [1, 4], "x": 4, "y": 2.75},
                {"label": "5", "matrix": [1, 5], "x": 5, "y": 2.75},
                {"label": "6", "matrix": [1, 6], "x": 6, "y": 2.75},
                {"label": "7", "matrix": [1, 7], "x": 7, "y": 2.75},
                {"label": "8", "matrix": [1, 8], "x": 8, "y": 2.75},
                {"label": "9", "matrix": [1, 9], "x": 9, "y": 2.75},
                {"label": "0", "matrix": [1, 10], "x": 10, "y": 2.75},
                {"label": "-", "matrix": [1, 11], "x": 11, "y": 2.75},
                {"label": "=", "matrix": [1, 12], "x": 12, "y": 2.75},
                {"label": "Delete", "matrix": [1, 13], "x": 13, "y": 2.75},
                {"label": "Backspace", "matrix": [1, 14], "x": 14, "y": 2.75},

                {"label": "Insert", "matrix": [1, 15], "x": 15.25, "y": 2.75},
                {"label": "Home", "matrix": [1, 16], "x": 16.25, "y": 2.75},
                {"label": "Page Up", "matrix": [1, 17], "x": 17.25, "y": 2.75},

                {"label": "Tab", "matrix": [2, 0], "x": 0, "y": 3.75, "w": 1.5},
                {"label": "Q", "matrix": [2, 1], "x": 1.5, "y": 3.75},
                {"label": "W", "matrix": [2, 2], "x": 2.5, "y": 3.75},
                {"label": "E", "matrix": [2, 3], "x": 3.5, "y": 3.75},
                {"label": "R", "matrix": [2, 4], "x": 4.5, "y": 3.75},
                {"label": "T", "matrix": [2, 5], "x": 5.5, "y": 3.75},
                {"label": "Y", "matrix": [2, 6], "x": 6.5, "y": 3.75},
                {"label": "U", "matrix": [2, 7], "x": 7.5, "y": 3.75},
                {"label": "I", "matrix": [2, 8], "x": 8.5, "y": 3.75},
                {"label": "O", "matrix": [2, 9], "x": 9.5, "y": 3.75},
                {"label": "P", "matrix": [2, 10], "x": 10.5, "y": 3.75},
                {"label": "[", "matrix": [2, 11], "x": 11.5, "y": 3.75},
                {"label": "]", "matrix": [2, 12], "x": 12.5, "y": 3.75},
                {"label": "\\", "matrix": [2, 13], "x": 13.5, "y": 3.75, "w": 1.5},

                {"label": "Delete", "matrix": [2, 15], "x": 15.25, "y": 3.75},
                {"label": "End", "matrix": [2, 16], "x": 16.25, "y": 3.75},
                {"label": "Page Down", "matrix": [2, 17], "x": 17.25, "y": 3.75},

                {"label": "Caps Lock", "matrix": [3, 0], "x": 0, "y": 4.75, "w": 1.75},
                {"label": "A", "matrix": [3, 1], "x": 1.75, "y": 4.75},
                {"label": "S", "matrix": [3, 2], "x": 2.75, "y": 4.75},
                {"label": "D", "matrix": [3, 3], "x": 3.75, "y": 4.75},
                {"label": "F", "matrix": [3, 4], "x": 4.75, "y": 4.75},
                {"label": "G", "matrix": [3, 5], "x": 5.75, "y": 4.75},
                {"label": "H", "matrix": [3, 6], "x": 6.75, "y": 4.75},
                {"label": "J", "matrix": [3, 7], "x": 7.75, "y": 4.75},
                {"label": "K", "matrix": [3, 8], "x": 8.75, "y": 4.75},
                {"label": "L", "matrix": [3, 9], "x": 9.75, "y": 4.75},
                {"label": ";", "matrix": [3, 10], "x": 10.75, "y": 4.75},
                {"label": "'", "matrix": [3, 11], "x": 11.75, "y": 4.75},
                {"label": "#", "matrix": [3, 12], "x": 12.75, "y": 4.75},
                {"label": "Enter", "matrix": [3, 13], "x": 13.75, "y": 4.75, "w": 1.25},

                {"label": "Shift", "matrix": [4, 0], "x": 0, "y": 5.75, "w": 1.25},
                {"label": "\\", "matrix": [4, 1], "x": 1.25, "y": 5.75},
                {"label": "Z", "matrix": [4, 2], "x": 2.25, "y": 5.75},
                {"label": "X", "matrix": [4, 3], "x": 3.25, "y": 5.75},
                {"label": "C", "matrix": [4, 4], "x": 4.25, "y": 5.75},
                {"label": "V", "matrix": [4, 5], "x": 5.25, "y": 5.75},
                {"label": "B", "matrix": [4, 6], "x": 6.25, "y": 5.75},
                {"label": "N", "matrix": [4, 7], "x": 7.25, "y": 5.75},
                {"label": "M", "matrix": [4, 8], "x": 8.25, "y": 5.75},
                {"label": ",", "matrix": [4, 9], "x": 9.25, "y": 5.75},
                {"label": ".", "matrix": [4, 10], "x": 10.25, "y": 5.75},
                {"label": "/", "matrix": [4, 11], "x": 11.25, "y": 5.75},
                {"label": "Shift", "matrix": [4, 12], "x": 12.25, "y": 5.75, "w": 1.75},
                {"label": "Fn", "matrix": [4, 13], "x": 14, "y": 5.75},

                {"label": "\u2191", "matrix": [4, 16], "x": 16.25, "y": 5.75},

                {"label": "Ctrl", "matrix": [5, 0], "x": 0, "y": 6.75, "w": 1.25},
                {"label": "GUI", "matrix": [5, 1], "x": 1.25, "y": 6.75, "w": 1.25},
                {"label": "Alt", "matrix": [5, 2], "x": 2.5, "y": 6.75, "w": 1.25},
                {"label": "Space", "matrix": [5, 6], "x": 3.75, "y": 6.75, "w": 6.25},
                {"label": "Alt", "matrix": [5, 9], "x": 10, "y": 6.75, "w": 1.25},
                {"label": "GUI", "matrix": [5, 10], "x": 11.25, "y": 6.75, "w": 1.25},
                {"label": "Fn", "matrix": [5, 11], "x": 12.5, "y": 6.75, "w": 1.25},
                {"label": "Ctrl", "matrix": [5, 12], "x": 13.75, "y": 6.75, "w": 1.25},

                {"label": "\u2190", "matrix": [5, 15], "x": 15.25, "y": 6.75},
                {"label": "\u2193", "matrix": [5, 16], "x": 16.25, "y": 6.75},
                {"label": "\u2192", "matrix": [5, 17], "x": 17.25, "y": 6.75}
            ]
        },
        "LAYOUT_ansi": {
            "layout": [
                {"label": "Play/Pause", "matrix": [4, 15], "x": 3, "y": 0},

                {"label": "Esc", "matrix": [0, 0], "x": 0, "y": 1.5},

                {"label": "F1", "matrix": [0, 1], "x": 2, "y": 1.5},
                {"label": "F2", "matrix": [0, 2], "x": 3, "y": 1.5},
                {"label": "F3", "matrix": [0, 3], "x": 4, "y": 1.5},
                {"label": "F4", "matrix": [0, 4], "x": 5, "y": 1.5},

                {"label": "F5", "matrix": [0, 5], "x": 6.5, "y": 1.5},
                {"label": "F6", "matrix": [0, 6], "x": 7.5, "y": 1.5},
                {"label": "F7", "matrix": [0, 7], "x": 8.5, "y": 1.5},
                {"label": "F8", "matrix": [0, 8], "x": 9.5, "y": 1.5},

                {"label": "F9", "matrix": [0, 9], "x": 11, "y": 1.5},
                {"label": "F10", "matrix": [0, 10], "x": 12, "y": 1.5},
                {"label": "F11", "matrix": [0, 11], "x": 13, "y": 1.5},
                {"label": "F12", "matrix": [0, 12], "x": 14, "y": 1.5},

                {"label": "`", "matrix": [1, 0], "x": 0, "y": 2.75},
                {"label": "1", "matrix": [1, 1], "x": 1, "y": 2.75},
                {"label": "2", "matrix": [1, 2], "x": 2, "y": 2.75},
                {"label": "3", "matrix": [1, 3], "x": 3, "y": 2.75},
                {"label": "4", "matrix": [1, 4], "x": 4, "y": 2.75},
                {"label": "5", "matrix": [1, 5], "x": 5, "y": 2.75},
                {"label": "6", "matrix": [1, 6], "x": 6, "y": 2.75},
                {"label": "7", "matrix": [1, 7], "x": 7, "y": 2.75},
                {"label": "8", "matrix": [1, 8], "x": 8, "y": 2.75},
                {"label": "9", "matrix": [1, 9], "x": 9, "y": 2.75},
                {"label": "0", "matrix": [1, 10], "x": 10, "y": 2.75},
                {"label": "-", "matrix": [1, 11], "x": 11, "y": 2.75},
                {"label": "=", "matrix": [1, 12], "x": 12, "y": 2.75},
                {"label": "Backspace", "matrix": [1, 14], "x": 13, "y": 2.75, "w": 2},

                {"label": "Insert", "matrix": [1, 15], "x": 15.25, "y": 2.75},
                {"label": "Home", "matrix": [1, 16], "x": 16.25, "y": 2.75},
                {"label": "Page Up", "matrix": [1, 17], "x": 17.25, "y": 2.75},

                {"label": "Tab", "matrix": [2, 0], "x": 0, "y": 3.75, "w": 1.5},
                {"label": "Q", "matrix": [2, 1], "x": 1.5, "y": 3.75},
                {"label": "W", "matrix": [2, 2], "x": 2.5, "y": 3.75},
                {"label": "E", "matrix": [2, 3], "x": 3.5, "y": 3.75},
                {"label": "R", "matrix": [2, 4], "x": 4.5, "y": 3.75},
                {"label": "T", "matrix": [2, 5], "x": 5.5, "y": 3.75},
                {"label": "Y", "matrix": [2, 6], "x": 6.5, "y": 3.75},
                {"label": "U", "matrix": [2, 7], "x": 7.5, "y": 3.75},
                {"label": "I", "matrix": [2, 8], "x": 8.5, "y": 3.75},
                {"label": "O", "matrix": [2, 9], "x": 9.5, "y": 3.75},
                {"label": "P", "matrix": [2, 10], "x": 10.5, "y": 3.75},
                {"label": "[", "matrix": [2, 11], "x": 11.5, "y": 3.75},
                {"label": "]", "matrix": [2, 12], "x": 12.5, "y": 3.75},
                {"label": "\\", "matrix": [2, 13], "x": 13.5, "y": 3.75, "w": 1.5},

                {"label": "Delete", "matrix": [2, 15], "x": 15.25, "y": 3.75},
                {"label": "End", "matrix": [2, 16], "x": 16.25, "y": 3.75},
                {"label": "Page Down", "matrix": [2, 17], "x": 17.25, "y": 3.75},

                {"label": "Caps Lock", "matrix": [3, 0], "x": 0, "y": 4.75, "w": 1.75},
                {"label": "A", "matrix": [3, 1], "x": 1.75, "y": 4.75},
                {"label": "S", "matrix": [3, 2], "x": 2.75, "y": 4.75},
                {"label": "D", "matrix": [3, 3], "x": 3.75, "y": 4.75},
                {"label": "F", "matrix": [3, 4], "x": 4.75, "y": 4.75},
                {"label": "G", "matrix": [3, 5], "x": 5.75, "y": 4.75},
                {"label": "H", "matrix": [3, 6], "x": 6.75, "y": 4.75},
                {"label": "J", "matrix": [3, 7], "x": 7.75, "y": 4.75},
                {"label": "K", "matrix": [3, 8], "x": 8.75, "y": 4.75},
                {"label": "L", "matrix": [3, 9], "x": 9.75, "y": 4.75},
                {"label": ";", "matrix": [3, 10], "x": 10.75, "y": 4.75},
                {"label": "'", "matrix": [3, 11], "x": 11.75, "y": 4.75},
                {"label": "Enter", "matrix": [3, 13], "x": 12.75, "y": 4.75, "w": 2.25},

                {"label": "Shift", "matrix": [4, 0], "x": 0, "y": 5.75, "w": 2.25},
                {"label": "Z", "matrix": [4, 2], "x": 2.25, "y": 5.75},
                {"label": "X", "matrix": [4, 3], "x": 3.25, "y": 5.75},
                {"label": "C", "matrix": [4, 4], "x": 4.25, "y": 5.75},
                {"label": "V", "matrix": [4, 5], "x": 5.25, "y": 5.75},
                {"label": "B", "matrix": [4, 6], "x": 6.25, "y": 5.75},
                {"label": "N", "matrix": [4, 7], "x": 7.25, "y": 5.75},
                {"label": "M", "matrix": [4, 8], "x": 8.25, "y": 5.75},
                {"label": ",", "matrix": [4, 9], "x": 9.25, "y": 5.75},
                {"label": ".", "matrix": [4, 10], "x": 10.25, "y": 5.75},
                {"label": "/", "matrix": [4, 11], "x": 11.25, "y": 5.75},
                {"label": "Shift", "matrix": [4, 12], "x": 12.25, "y": 5.75, "w": 2.75},

                {"label": "\u2191", "matrix": [4, 16], "x": 16.25, "y": 5.75},

                {"label": "Ctrl", "matrix": [5, 0], "x": 0, "y": 6.75, "w": 1.25},
                {"label": "GUI", "matrix": [5, 1], "x": 1.25, "y": 6.75, "w": 1.25},
                {"label": "Alt", "matrix": [5, 2], "x": 2.5, "y": 6.75, "w": 1.25},
                {"label": "Space", "matrix": [5, 6], "x": 3.75, "y": 6.75, "w": 6.25},
                {"label": "Alt", "matrix": [5, 9], "x": 10, "y": 6.75, "w": 1.25},
                {"label": "GUI", "matrix": [5, 10], "x": 11.25, "y": 6.75, "w": 1.25},
                {"label": "Fn", "matrix": [5, 11], "x": 12.5, "y": 6.75, "w": 1.25},
                {"label": "Ctrl", "matrix": [5, 12], "x": 13.75, "y": 6.75, "w": 1.25},

                {"label": "\u2190", "matrix": [5, 15], "x": 15.25, "y": 6.75},
                {"label": "\u2193", "matrix": [5, 16], "x": 16.25, "y": 6.75},
                {"label": "\u2192", "matrix": [5, 17], "x": 17.25, "y": 6.75}
            ]
        },
        "LAYOUT_ansi_split_bs_rshift": {
            "layout": [
                {"label": "Play/Pause", "matrix": [4, 15], "x": 3, "y": 0},

                {"label": "Esc", "matrix": [0, 0], "x": 0, "y": 1.5},

                {"label": "F1", "matrix": [0, 1], "x": 2, "y": 1.5},
                {"label": "F2", "matrix": [0, 2], "x": 3, "y": 1.5},
                {"label": "F3", "matrix": [0, 3], "x": 4, "y": 1.5},
                {"label": "F4", "matrix": [0, 4], "x": 5, "y": 1.5},

                {"label": "F5", "matrix": [0, 5], "x": 6.5, "y": 1.5},
                {"label": "F6", "matrix": [0, 6], "x": 7.5, "y": 1.5},
                {"label": "F7", "matrix": [0, 7], "x": 8.5, "y": 1.5},
                {"label": "F8", "matrix": [0, 8], "x": 9.5, "y": 1.5},

                {"label": "F9", "matrix": [0, 9], "x": 11, "y": 1.5},
                {"label": "F10", "matrix": [0, 10], "x": 12, "y": 1.5},
                {"label": "F11", "matrix": [0, 11], "x": 13, "y": 1.5},
                {"label": "F12", "matrix": [0, 12], "x": 14, "y": 1.5},

                {"label": "`", "matrix": [1, 0], "x": 0, "y": 2.75},
                {"label": "1", "matrix": [1, 1], "x": 1, "y": 2.75},
                {"label": "2", "matrix": [1, 2], "x": 2, "y": 2.75},
                {"label": "3", "matrix": [1, 3], "x": 3, "y": 2.75},
                {"label": "4", "matrix": [1, 4], "x": 4, "y": 2.75},
                {"label": "5", "matrix": [1, 5], "x": 5, "y": 2.75},
                {"label": "6", "matrix": [1, 6], "x": 6, "y": 2.75},
                {"label": "7", "matrix": [1, 7], "x": 7, "y": 2.75},
                {"label": "8", "matrix": [1, 8], "x": 8, "y": 2.75},
                {"label": "9", "matrix": [1, 9], "x": 9, "y": 2.75},
                {"label": "0", "matrix": [1, 10], "x": 10, "y": 2.75},
                {"label": "-", "matrix": [1, 11], "x": 11, "y": 2.75},
                {"label": "=", "matrix": [1, 12], "x": 12, "y": 2.75},
                {"label": "Delete", "matrix": [1, 13], "x": 13, "y": 2.75},
                {"label": "Backspace", "matrix": [1, 14], "x": 14, "y": 2.75},

                {"label": "Insert", "matrix": [1, 15], "x": 15.25, "y": 2.75},
                {"label": "Home", "matrix": [1, 16], "x": 16.25, "y": 2.75},
                {"label": "Page Up", "matrix": [1, 17], "x": 17.25, "y": 2.75},

                {"label": "Tab", "matrix": [2, 0], "x": 0, "y": 3.75, "w": 1.5},
                {"label": "Q", "matrix": [2, 1], "x": 1.5, "y": 3.75},
                {"label": "W", "matrix": [2, 2], "x": 2.5, "y": 3.75},
                {"label": "E", "matrix": [2, 3], "x": 3.5, "y": 3.75},
                {"label": "R", "matrix": [2, 4], "x": 4.5, "y": 3.75},
                {"label": "T", "matrix": [2, 5], "x": 5.5, "y": 3.75},
                {"label": "Y", "matrix": [2, 6], "x": 6.5, "y": 3.75},
                {"label": "U", "matrix": [2, 7], "x": 7.5, "y": 3.75},
                {"label": "I", "matrix": [2, 8], "x": 8.5, "y": 3.75},
                {"label": "O", "matrix": [2, 9], "x": 9.5, "y": 3.75},
                {"label": "P", "matrix": [2, 10], "x": 10.5, "y": 3.75},
                {"label": "[", "matrix": [2, 11], "x": 11.5, "y": 3.75},
                {"label": "]", "matrix": [2, 12], "x": 12.5, "y": 3.75},
                {"label": "\\", "matrix": [2, 13], "x": 13.5, "y": 3.75, "w": 1.5},

                {"label": "Delete", "matrix": [2, 15], "x": 15.25, "y": 3.75},
                {"label": "End", "matrix": [2, 16], "x": 16.25, "y": 3.75},
                {"label": "Page Down", "matrix": [2, 17], "x": 17.25, "y": 3.75},

                {"label": "Caps Lock", "matrix": [3, 0], "x": 0, "y": 4.75, "w": 1.75},
                {"label": "A", "matrix": [3, 1], "x": 1.75, "y": 4.75},
                {"label": "S", "matrix": [3, 2], "x": 2.75, "y": 4.75},
                {"label": "D", "matrix": [3, 3], "x": 3.75, "y": 4.75},
                {"label": "F", "matrix": [3, 4], "x": 4.75, "y": 4.75},
                {"label": "G", "matrix": [3, 5], "x": 5.75, "y": 4.75},
                {"label": "H", "matrix": [3, 6], "x": 6.75, "y": 4.75},
                {"label": "J", "matrix": [3, 7], "x": 7.75, "y": 4.75},
                {"label": "K", "matrix": [3, 8], "x": 8.75, "y": 4.75},
                {"label": "L", "matrix": [3, 9], "x": 9.75, "y": 4.75},
                {"label": ";", "matrix": [3, 10], "x": 10.75, "y": 4.75},
                {"label": "'", "matrix": [3, 11], "x": 11.75, "y": 4.75},
                {"label": "Enter", "matrix": [3, 13], "x": 12.75, "y": 4.75, "w": 2.25},

                {"label": "Shift", "matrix": [4, 0], "x": 0, "y": 5.75, "w": 2.25},
                {"label": "Z", "matrix": [4, 2], "x": 2.25, "y": 5.75},
                {"label": "X", "matrix": [4, 3], "x": 3.25, "y": 5.75},
                {"label": "C", "matrix": [4, 4], "x": 4.25, "y": 5.75},
                {"label": "V", "matrix": [4, 5], "x": 5.25, "y": 5.75},
                {"label": "B", "matrix": [4, 6], "x": 6.25, "y": 5.75},
                {"label": "N", "matrix": [4, 7], "x": 7.25, "y": 5.75},
                {"label": "M", "matrix": [4, 8], "x": 8.25, "y": 5.75},
                {"label": ",", "matrix": [4, 9], "x": 9.25, "y": 5.75},
                {"label": ".", "matrix": [4, 10], "x": 10.25, "y": 5.75},
                {"label": "/", "matrix": [4, 11], "x": 11.25, "y": 5.75},
                {"label": "Shift", "matrix": [4, 12], "x": 12.25, "y": 5.75, "w": 1.75},
                {"label": "Fn", "matrix": [4, 13], "x": 14, "y": 5.75},

                {"label": "\u2191", "matrix": [4, 16], "x": 16.25, "y": 5.75},

                {"label": "Ctrl", "matrix": [5, 0], "x": 0, "y": 6.75, "w": 1.25},
                {"label": "GUI", "matrix": [5, 1], "x": 1.25, "y": 6.75, "w": 1.25},
                {"label": "Alt", "matrix": [5, 2], "x": 2.5, "y": 6.75, "w": 1.25},
                {"label": "Space", "matrix": [5, 6], "x": 3.75, "y": 6.75, "w": 6.25},
                {"label": "Alt", "matrix": [5, 9], "x": 10, "y": 6.75, "w": 1.25},
                {"label": "GUI", "matrix": [5, 10], "x": 11.25, "y": 6.75, "w": 1.25},
                {"label": "Fn", "matrix": [5, 11], "x": 12.5, "y": 6.75, "w": 1.25},
                {"label": "Ctrl", "matrix": [5, 12], "x": 13.75, "y": 6.75, "w": 1.25},

                {"label": "\u2190", "matrix": [5, 15], "x": 15.25, "y": 6.75},
                {"label": "\u2193", "matrix": [5, 16], "x": 16.25, "y": 6.75},
                {"label": "\u2192", "matrix": [5, 17], "x": 17.25, "y": 6.75}
            ]
        },
        "LAYOUT_ansi_tsangan": {
            "layout": [
                {"label": "Play/Pause", "matrix": [4, 15], "x": 3, "y": 0},

                {"label": "Esc", "matrix": [0, 0], "x": 0, "y": 1.5},

                {"label": "F1", "matrix": [0, 1], "x": 2, "y": 1.5},
                {"label": "F2", "matrix": [0, 2], "x": 3, "y": 1.5},
                {"label": "F3", "matrix": [0, 3], "x": 4, "y": 1.5},
                {"label": "F4", "matrix": [0, 4], "x": 5, "y": 1.5},

                {"label": "F5", "matrix": [0, 5], "x": 6.5, "y": 1.5},
                {"label": "F6", "matrix": [0, 6], "x": 7.5, "y": 1.5},
                {"label": "F7", "matrix": [0, 7], "x": 8.5, "y": 1.5},
                {"label": "F8", "matrix": [0, 8], "x": 9.5, "y": 1.5},

                {"label": "F9", "matrix": [0, 9], "x": 11, "y": 1.5},
                {"label": "F10", "matrix": [0, 10], "x": 12, "y": 1.5},
                {"label": "F11", "matrix": [0, 11], "x": 13, "y": 1.5},
                {"label": "F12", "matrix": [0, 12], "x": 14, "y": 1.5},

                {"label": "`", "matrix": [1, 0], "x": 0, "y": 2.75},
                {"label": "1", "matrix": [1, 1], "x": 1, "y": 2.75},
                {"label": "2", "matrix": [1, 2], "x": 2, "y": 2.75},
                {"label": "3", "matrix": [1, 3], "x": 3, "y": 2.75},
                {"label": "4", "matrix": [1, 4], "x": 4, "y": 2.75},
                {"label": "5", "matrix": [1, 5], "x": 5, "y": 2.75},
                {"label": "6", "matrix": [1, 6], "x": 6, "y": 2.75},
                {"label": "7", "matrix": [1, 7], "x": 7, "y": 2.75},
                {"label": "8", "matrix": [1, 8], "x": 8, "y": 2.75},
                {"label": "9", "matrix": [1, 9], "x": 9, "y": 2.75},
                {"label": "0", "matrix": [1, 10], "x": 10, "y": 2.75},
                {"label": "-", "matrix": [1, 11], "x": 11, "y": 2.75},
                {"label": "=", "matrix": [1, 12], "x": 12, "y": 2.75},
                {"label": "Backspace", "matrix": [1, 14], "x": 13, "y": 2.75, "w": 2},

                {"label": "Insert", "matrix": [1, 15], "x": 15.25, "y": 2.75},
                {"label": "Home", "matrix": [1, 16], "x": 16.25, "y": 2.75},
                {"label": "Page Up", "matrix": [1, 17], "x": 17.25, "y": 2.75},

                {"label": "Tab", "matrix": [2, 0], "x": 0, "y": 3.75, "w": 1.5},
                {"label": "Q", "matrix": [2, 1], "x": 1.5, "y": 3.75},
                {"label": "W", "matrix": [2, 2], "x": 2.5, "y": 3.75},
                {"label": "E", "matrix": [2, 3], "x": 3.5, "y": 3.75},
                {"label": "R", "matrix": [2, 4], "x": 4.5, "y": 3.75},
                {"label": "T", "matrix": [2, 5], "x": 5.5, "y": 3.75},
                {"label": "Y", "matrix": [2, 6], "x": 6.5, "y": 3.75},
                {"label": "U", "matrix": [2, 7], "x": 7.5, "y": 3.75},
                {"label": "I", "matrix": [2, 8], "x": 8.5, "y": 3.75},
                {"label": "O", "matrix": [2, 9], "x": 9.5, "y": 3.75},
                {"label": "P", "matrix": [2, 10], "x": 10.5, "y": 3.75},
                {"label": "[", "matrix": [2, 11], "x": 11.5, "y": 3.75},
                {"label": "]", "matrix": [2, 12], "x": 12.5, "y": 3.75},
                {"label": "\\", "matrix": [2, 13], "x": 13.5, "y": 3.75, "w": 1.5},

                {"label": "Delete", "matrix": [2, 15], "x": 15.25, "y": 3.75},
                {"label": "End", "matrix": [2, 16], "x": 16.25, "y": 3.75},
                {"label": "Page Down", "matrix": [2, 17], "x": 17.25, "y": 3.75},

                {"label": "Caps Lock", "matrix": [3, 0], "x": 0, "y": 4.75, "w": 1.75},
                {"label": "A", "matrix": [3, 1], "x": 1.75, "y": 4.75},
                {"label": "S", "matrix": [3, 2], "x": 2.75, "y": 4.75},
                {"label": "D", "matrix": [3, 3], "x": 3.75, "y": 4.75},
                {"label": "F", "matrix": [3, 4], "x": 4.75, "y": 4.75},
                {"label": "G", "matrix": [3, 5], "x": 5.75, "y": 4.75},
                {"label": "H", "matrix": [3, 6], "x": 6.75, "y": 4.75},
                {"label": "J", "matrix": [3, 7], "x": 7.75, "y": 4.75},
                {"label": "K", "matrix": [3, 8], "x": 8.75, "y": 4.75},
                {"label": "L", "matrix": [3, 9], "x": 9.75, "y": 4.75},
                {"label": ";", "matrix": [3, 10], "x": 10.75, "y": 4.75},
                {"label": "'", "matrix": [3, 11], "x": 11.75, "y": 4.75},
                {"label": "Enter", "matrix": [3, 13], "x": 12.75, "y": 4.75, "w": 2.25},

                {"label": "Shift", "matrix": [4, 0], "x": 0, "y": 5.75, "w": 2.25},
                {"label": "Z", "matrix": [4, 2], "x": 2.25, "y": 5.75},
                {"label": "X", "matrix": [4, 3], "x": 3.25, "y": 5.75},
                {"label": "C", "matrix": [4, 4], "x": 4.25, "y": 5.75},
                {"label": "V", "matrix": [4, 5], "x": 5.25, "y": 5.75},
                {"label": "B", "matrix": [4, 6], "x": 6.25, "y": 5.75},
                {"label": "N", "matrix": [4, 7], "x": 7.25, "y": 5.75},
                {"label": "M", "matrix": [4, 8], "x": 8.25, "y": 5.75},
                {"label": ",", "matrix": [4, 9], "x": 9.25, "y": 5.75},
                {"label": ".", "matrix": [4, 10], "x": 10.25, "y": 5.75},
                {"label": "/", "matrix": [4, 11], "x": 11.25, "y": 5.75},
                {"label": "Shift", "matrix": [4, 12], "x": 12.25, "y": 5.75, "w": 2.75},

                {"label": "\u2191", "matrix": [4, 16], "x": 16.25, "y": 5.75},

                {"label": "Ctrl", "matrix": [5, 0], "x": 0, "y": 6.75, "w": 1.5},
                {"label": "GUI", "matrix": [5, 1], "x": 1.5, "y": 6.75},
                {"label": "Alt", "matrix": [5, 2], "x": 2.5, "y": 6.75, "w": 1.5},
                {"label": "Space", "matrix": [5, 6], "x": 4, "y": 6.75, "w": 7},
                {"label": "Alt", "matrix": [5, 10], "x": 11, "y": 6.75, "w": 1.5},
                {"label": "Fn", "matrix": [5, 11], "x": 12.5, "y": 6.75},
                {"label": "Ctrl", "matrix": [5, 12], "x": 13.5, "y": 6.75, "w": 1.5},

                {"label": "\u2190", "matrix": [5, 15], "x": 15.25, "y": 6.75},
                {"label": "\u2193", "matrix": [5, 16], "x": 16.25, "y": 6.75},
                {"label": "\u2192", "matrix": [5, 17], "x": 17.25, "y": 6.75}
            ]
        },
        "LAYOUT_ansi_tsangan_split_bs_rshift": {
            "layout": [
                {"label": "Play/Pause", "matrix": [4, 15], "x": 3, "y": 0},

                {"label": "Esc", "matrix": [0, 0], "x": 0, "y": 1.5},

                {"label": "F1", "matrix": [0, 1], "x": 2, "y": 1.5},
                {"label": "F2", "matrix": [0, 2], "x": 3, "y": 1.5},
                {"label": "F3", "matrix": [0, 3], "x": 4, "y": 1.5},
                {"label": "F4", "matrix": [0, 4], "x": 5, "y": 1.5},

                {"label": "F5", "matrix": [0, 5], "x": 6.5, "y": 1.5},
                {"label": "F6", "matrix": [0, 6], "x": 7.5, "y": 1.5},
                {"label": "F7", "matrix": [0, 7], "x": 8.5, "y": 1.5},
                {"label": "F8", "matrix": [0, 8], "x": 9.5, "y": 1.5},

                {"label": "F9", "matrix": [0, 9], "x": 11, "y": 1.5},
                {"label": "F10", "matrix": [0, 10], "x": 12, "y": 1.5},
                {"label": "F11", "matrix": [0, 11], "x": 13, "y": 1.5},
                {"label": "F12", "matrix": [0, 12], "x": 14, "y": 1.5},

                {"label": "`", "matrix": [1, 0], "x": 0, "y": 2.75},
                {"label": "1", "matrix": [1, 1], "x": 1, "y": 2.75},
                {"label": "2", "matrix": [1, 2], "x": 2, "y": 2.75},
                {"label": "3", "matrix": [1, 3], "x": 3, "y": 2.75},
                {"label": "4", "matrix": [1, 4], "x": 4, "y": 2.75},
                {"label": "5", "matrix": [1, 5], "x": 5, "y": 2.75},
                {"label": "6", "matrix": [1, 6], "x": 6, "y": 2.75},
                {"label": "7", "matrix": [1, 7], "x": 7, "y": 2.75},
                {"label": "8", "matrix": [1, 8], "x": 8, "y": 2.75},
                {"label": "9", "matrix": [1, 9], "x": 9, "y": 2.75},
                {"label": "0", "matrix": [1, 10], "x": 10, "y": 2.75},
                {"label": "-", "matrix": [1, 11], "x": 11, "y": 2.75},
                {"label": "=", "matrix": [1, 12], "x": 12, "y": 2.75},
                {"label": "Delete", "matrix": [1, 13], "x": 13, "y": 2.75},
                {"label": "Backspace", "matrix": [1, 14], "x": 14, "y": 2.75},

                {"label": "Insert", "matrix": [1, 15], "x": 15.25, "y": 2.75},
                {"label": "Home", "matrix": [1, 16], "x": 16.25, "y": 2.75},
                {"label": "Page Up", "matrix": [1, 17], "x": 17.25, "y": 2.75},

                {"label": "Tab", "matrix": [2, 0], "x": 0, "y": 3.75, "w": 1.5},
                {"label": "Q", "matrix": [2, 1], "x": 1.5, "y": 3.75},
                {"label": "W", "matrix": [2, 2], "x": 2.5, "y": 3.75},
                {"label": "E", "matrix": [2, 3], "x": 3.5, "y": 3.75},
                {"label": "R", "matrix": [2, 4], "x": 4.5, "y": 3.75},
                {"label": "T", "matrix": [2, 5], "x": 5.5, "y": 3.75},
                {"label": "Y", "matrix": [2, 6], "x": 6.5, "y": 3.75},
                {"label": "U", "matrix": [2, 7], "x": 7.5, "y": 3.75},
                {"label": "I", "matrix": [2, 8], "x": 8.5, "y": 3.75},
                {"label": "O", "matrix": [2, 9], "x": 9.5, "y": 3.75},
                {"label": "P", "matrix": [2, 10], "x": 10.5, "y": 3.75},
                {"label": "[", "matrix": [2, 11], "x": 11.5, "y": 3.75},
                {"label": "]", "matrix": [2, 12], "x": 12.5, "y": 3.75},
                {"label": "\\", "matrix": [2, 13], "x": 13.5, "y": 3.75, "w": 1.5},

                {"label": "Delete", "matrix": [2, 15], "x": 15.25, "y": 3.75},
                {"label": "End", "matrix": [2, 16], "x": 16.25, "y": 3.75},
                {"label": "Page Down", "matrix": [2, 17], "x": 17.25, "y": 3.75},

                {"label": "Caps Lock", "matrix": [3, 0], "x": 0, "y": 4.75, "w": 1.75},
                {"label": "A", "matrix": [3, 1], "x": 1.75, "y": 4.75},
                {"label": "S", "matrix": [3, 2], "x": 2.75, "y": 4.75},
                {"label": "D", "matrix": [3, 3], "x": 3.75, "y": 4.75},
                {"label": "F", "matrix": [3, 4], "x": 4.75, "y": 4.75},
                {"label": "G", "matrix": [3, 5], "x": 5.75, "y": 4.75},
                {"label": "H", "matrix": [3, 6], "x": 6.75, "y": 4.75},
                {"label": "J", "matrix": [3, 7], "x": 7.75, "y": 4.75},
                {"label": "K", "matrix": [3, 8], "x": 8.75, "y": 4.75},
                {"label": "L", "matrix": [3, 9], "x": 9.75, "y": 4.75},
                {"label": ";", "matrix": [3, 10], "x": 10.75, "y": 4.75},
                {"label": "'", "matrix": [3, 11], "x": 11.75, "y": 4.75},
                {"label": "Enter", "matrix": [3, 13], "x": 12.75, "y": 4.75, "w": 2.25},

                {"label": "Shift", "matrix": [4, 0], "x": 0, "y": 5.75, "w": 2.25},
                {"label": "Z", "matrix": [4, 2], "x": 2.25, "y": 5.75},
                {"label": "X", "matrix": [4, 3], "x": 3.25, "y": 5.75},
                {"label": "C", "matrix": [4, 4], "x": 4.25, "y": 5.75},
                {"label": "V", "matrix": [4, 5], "x": 5.25, "y": 5.75},
                {"label": "B", "matrix": [4, 6], "x": 6.25, "y": 5.75},
                {"label": "N", "matrix": [4, 7], "x": 7.25, "y": 5.75},
                {"label": "M", "matrix": [4, 8], "x": 8.25, "y": 5.75},
                {"label": ",", "matrix": [4, 9], "x": 9.25, "y": 5.75},
                {"label": ".", "matrix": [4, 10], "x": 10.25, "y": 5.75},
                {"label": "/", "matrix": [4, 11], "x": 11.25, "y": 5.75},
                {"label": "Shift", "matrix": [4, 12], "x": 12.25, "y": 5.75, "w": 1.75},
                {"label": "Fn", "matrix": [4, 13], "x": 14, "y": 5.75},

                {"label": "\u2191", "matrix": [4, 16], "x": 16.25, "y": 5.75},

                {"label": "Ctrl", "matrix": [5, 0], "x": 0, "y": 6.75, "w": 1.5},
                {"label": "GUI", "matrix": [5, 1], "x": 1.5, "y": 6.75},
                {"label": "Alt", "matrix": [5, 2], "x": 2.5, "y": 6.75, "w": 1.5},
                {"label": "Space", "matrix": [5, 6], "x": 4, "y": 6.75, "w": 7},
                {"label": "Alt", "matrix": [5, 10], "x": 11, "y": 6.75, "w": 1.5},
                {"label": "Fn", "matrix": [5, 11], "x": 12.5, "y": 6.75},
                {"label": "Ctrl", "matrix": [5, 12], "x": 13.5, "y": 6.75, "w": 1.5},

                {"label": "\u2190", "matrix": [5, 15], "x": 15.25, "y": 6.75},
                {"label": "\u2193", "matrix": [5, 16], "x": 16.25, "y": 6.75},
                {"label": "\u2192", "matrix": [5, 17], "x": 17.25, "y": 6.75}
            ]
        },
        "LAYOUT_ansi_wkl": {
            "layout": [
                {"label": "Play/Pause", "matrix": [4, 15], "x": 3, "y": 0},

                {"label": "Esc", "matrix": [0, 0], "x": 0, "y": 1.5},

                {"label": "F1", "matrix": [0, 1], "x": 2, "y": 1.5},
                {"label": "F2", "matrix": [0, 2], "x": 3, "y": 1.5},
                {"label": "F3", "matrix": [0, 3], "x": 4, "y": 1.5},
                {"label": "F4", "matrix": [0, 4], "x": 5, "y": 1.5},

                {"label": "F5", "matrix": [0, 5], "x": 6.5, "y": 1.5},
                {"label": "F6", "matrix": [0, 6], "x": 7.5, "y": 1.5},
                {"label": "F7", "matrix": [0, 7], "x": 8.5, "y": 1.5},
                {"label": "F8", "matrix": [0, 8], "x": 9.5, "y": 1.5},

                {"label": "F9", "matrix": [0, 9], "x": 11, "y": 1.5},
                {"label": "F10", "matrix": [0, 10], "x": 12, "y": 1.5},
                {"label": "F11", "matrix": [0, 11], "x": 13, "y": 1.5},
                {"label": "F12", "matrix": [0, 12], "x": 14, "y": 1.5},

                {"label": "`", "matrix": [1, 0], "x": 0, "y": 2.75},
                {"label": "1", "matrix": [1, 1], "x": 1, "y": 2.75},
                {"label": "2", "matrix": [1, 2], "x": 2, "y": 2.75},
                {"label": "3", "matrix": [1, 3], "x": 3, "y": 2.75},
                {"label": "4", "matrix": [1, 4], "x": 4, "y": 2.75},
                {"label": "5", "matrix": [1, 5], "x": 5, "y": 2.75},
                {"label": "6", "matrix": [1, 6], "x": 6, "y": 2.75},
                {"label": "7", "matrix": [1, 7], "x": 7, "y": 2.75},
                {"label": "8", "matrix": [1, 8], "x": 8, "y": 2.75},
                {"label": "9", "matrix": [1, 9], "x": 9, "y": 2.75},
                {"label": "0", "matrix": [1, 10], "x": 10, "y": 2.75},
                {"label": "-", "matrix": [1, 11], "x": 11, "y": 2.75},
                {"label": "=", "matrix": [1, 12], "x": 12, "y": 2.75},
                {"label": "Backspace", "matrix": [1, 14], "x": 13, "y": 2.75, "w": 2},

                {"label": "Insert", "matrix": [1, 15], "x": 15.25, "y": 2.75},
                {"label": "Home", "matrix": [1, 16], "x": 16.25, "y": 2.75},
                {"label": "Page Up", "matrix": [1, 17], "x": 17.25, "y": 2.75},

                {"label": "Tab", "matrix": [2, 0], "x": 0, "y": 3.75, "w": 1.5},
                {"label": "Q", "matrix": [2, 1], "x": 1.5, "y": 3.75},
                {"label": "W", "matrix": [2, 2], "x": 2.5, "y": 3.75},
                {"label": "E", "matrix": [2, 3], "x": 3.5, "y": 3.75},
                {"label": "R", "matrix": [2, 4], "x": 4.5, "y": 3.75},
                {"label": "T", "matrix": [2, 5], "x": 5.5, "y": 3.75},
                {"label": "Y", "matrix": [2, 6], "x": 6.5, "y": 3.75},
                {"label": "U", "matrix": [2, 7], "x": 7.5, "y": 3.75},
                {"label": "I", "matrix": [2, 8], "x": 8.5, "y": 3.75},
                {"label": "O", "matrix": [2, 9], "x": 9.5, "y": 3.75},
                {"label": "P", "matrix": [2, 10], "x": 10.5, "y": 3.75},
                {"label": "[", "matrix": [2, 11], "x": 11.5, "y": 3.75},
                {"label": "]", "matrix": [2, 12], "x": 12.5, "y": 3.75},
                {"label": "\\", "matrix": [2, 13], "x": 13.5, "y": 3.75, "w": 1.5},

                {"label": "Delete", "matrix": [2, 15], "x": 15.25, "y": 3.75},
                {"label": "End", "matrix": [2, 16], "x": 16.25, "y": 3.75},
                {"label": "Page Down", "matrix": [2, 17], "x": 17.25, "y": 3.75},

                {"label": "Caps Lock", "matrix": [3, 0], "x": 0, "y": 4.75, "w": 1.75},
                {"label": "A", "matrix": [3, 1], "x": 1.75, "y": 4.75},
                {"label": "S", "matrix": [3, 2], "x": 2.75, "y": 4.75},
                {"label": "D", "matrix": [3, 3], "x": 3.75, "y": 4.75},
                {"label": "F", "matrix": [3, 4], "x": 4.75, "y": 4.75},
                {"label": "G", "matrix": [3, 5], "x": 5.75, "y": 4.75},
                {"label": "H", "matrix": [3, 6], "x": 6.75, "y": 4.75},
                {"label": "J", "matrix": [3, 7], "x": 7.75, "y": 4.75},
                {"label": "K", "matrix": [3, 8], "x": 8.75, "y": 4.75},
                {"label": "L", "matrix": [3, 9], "x": 9.75, "y": 4.75},
                {"label": ";", "matrix": [3, 10], "x": 10.75, "y": 4.75},
                {"label": "'", "matrix": [3, 11], "x": 11.75, "y": 4.75},
                {"label": "Enter", "matrix": [3, 13], "x": 12.75, "y": 4.75, "w": 2.25},

                {"label": "Shift", "matrix": [4, 0], "x": 0, "y": 5.75, "w": 2.25},
                {"label": "Z", "matrix": [4, 2], "x": 2.25, "y": 5.75},
                {"label": "X", "matrix": [4, 3], "x": 3.25, "y": 5.75},
                {"label": "C", "matrix": [4, 4], "x": 4.25, "y": 5.75},
                {"label": "V", "matrix": [4, 5], "x": 5.25, "y": 5.75},
                {"label": "B", "matrix": [4, 6], "x": 6.25, "y": 5.75},
                {"label": "N", "matrix": [4, 7], "x": 7.25, "y": 5.75},
                {"label": "M", "matrix": [4, 8], "x": 8.25, "y": 5.75},
                {"label": ",", "matrix": [4, 9], "x": 9.25, "y": 5.75},
                {"label": ".", "matrix": [4, 10], "x": 10.25, "y": 5.75},
                {"label": "/", "matrix": [4, 11], "x": 11.25, "y": 5.75},
                {"label": "Shift", "matrix": [4, 12], "x": 12.25, "y": 5.75, "w": 2.75},

                {"label": "\u2191", "matrix": [4, 16], "x": 16.25, "y": 5.75},

                {"label": "Ctrl", "matrix": [5, 0], "x": 0, "y": 6.75, "w": 1.5},
                {"label": "Alt", "matrix": [5, 2], "x": 2.5, "y": 6.75, "w": 1.5},
                {"label": "Space", "matrix": [5, 6], "x": 4, "y": 6.75, "w": 7},
                {"label": "Alt", "matrix": [5, 10], "x": 11, "y": 6.75, "w": 1.5},
                {"label": "Ctrl", "matrix": [5, 12], "x": 13.5, "y": 6.75, "w": 1.5},

                {"label": "\u2190", "matrix": [5, 15], "x": 15.25, "y": 6.75},
                {"label": "\u2193", "matrix": [5, 16], "x": 16.25, "y": 6.75},
                {"label": "\u2192", "matrix": [5, 17], "x": 17.25, "y": 6.75}
            ]
        },
        "LAYOUT_ansi_wkl_split_bs_rshift": {
            "layout": [
                {"label": "Play/Pause", "matrix": [4, 15], "x": 3, "y": 0},

                {"label": "Esc", "matrix": [0, 0], "x": 0, "y": 1.5},

                {"label": "F1", "matrix": [0, 1], "x": 2, "y": 1.5},
                {"label": "F2", "matrix": [0, 2], "x": 3, "y": 1.5},
                {"label": "F3", "matrix": [0, 3], "x": 4, "y": 1.5},
                {"label": "F4", "matrix": [0, 4], "x": 5, "y": 1.5},

                {"label": "F5", "matrix": [0, 5], "x": 6.5, "y": 1.5},
                {"label": "F6", "matrix": [0, 6], "x": 7.5, "y": 1.5},
                {"label": "F7", "matrix": [0, 7], "x": 8.5, "y": 1.5},
                {"label": "F8", "matrix": [0, 8], "x": 9.5, "y": 1.5},

                {"label": "F9", "matrix": [0, 9], "x": 11, "y": 1.5},
                {"label": "F10", "matrix": [0, 10], "x": 12, "y": 1.5},
                {"label": "F11", "matrix": [0, 11], "x": 13, "y": 1.5},
                {"label": "F12", "matrix": [0, 12], "x": 14, "y": 1.5},

                {"label": "`", "matrix": [1, 0], "x": 0, "y": 2.75},
                {"label": "1", "matrix": [1, 1], "x": 1, "y": 2.75},
                {"label": "2", "matrix": [1, 2], "x": 2, "y": 2.75},
                {"label": "3", "matrix": [1, 3], "x": 3, "y": 2.75},
                {"label": "4", "matrix": [1, 4], "x": 4, "y": 2.75},
                {"label": "5", "matrix": [1, 5], "x": 5, "y": 2.75},
                {"label": "6", "matrix": [1, 6], "x": 6, "y": 2.75},
                {"label": "7", "matrix": [1, 7], "x": 7, "y": 2.75},
                {"label": "8", "matrix": [1, 8], "x": 8, "y": 2.75},
                {"label": "9", "matrix": [1, 9], "x": 9, "y": 2.75},
                {"label": "0", "matrix": [1, 10], "x": 10, "y": 2.75},
                {"label": "-", "matrix": [1, 11], "x": 11, "y": 2.75},
                {"label": "=", "matrix": [1, 12], "x": 12, "y": 2.75},
                {"label": "Delete", "matrix": [1, 13], "x": 13, "y": 2.75},
                {"label": "Backspace", "matrix": [1, 14], "x": 14, "y": 2.75},

                {"label": "Insert", "matrix": [1, 15], "x": 15.25, "y": 2.75},
                {"label": "Home", "matrix": [1, 16], "x": 16.25, "y": 2.75},
                {"label": "Page Up", "matrix": [1, 17], "x": 17.25, "y": 2.75},

                {"label": "Tab", "matrix": [2, 0], "x": 0, "y": 3.75, "w": 1.5},
                {"label": "Q", "matrix": [2, 1], "x": 1.5, "y": 3.75},
                {"label": "W", "matrix": [2, 2], "x": 2.5, "y": 3.75},
                {"label": "E", "matrix": [2, 3], "x": 3.5, "y": 3.75},
                {"label": "R", "matrix": [2, 4], "x": 4.5, "y": 3.75},
                {"label": "T", "matrix": [2, 5], "x": 5.5, "y": 3.75},
                {"label": "Y", "matrix": [2, 6], "x": 6.5, "y": 3.75},
                {"label": "U", "matrix": [2, 7], "x": 7.5, "y": 3.75},
                {"label": "I", "matrix": [2, 8], "x": 8.5, "y": 3.75},
                {"label": "O", "matrix": [2, 9], "x": 9.5, "y": 3.75},
                {"label": "P", "matrix": [2, 10], "x": 10.5, "y": 3.75},
                {"label": "[", "matrix": [2, 11], "x": 11.5, "y": 3.75},
                {"label": "]", "matrix": [2, 12], "x": 12.5, "y": 3.75},
                {"label": "\\", "matrix": [2, 13], "x": 13.5, "y": 3.75, "w": 1.5},

                {"label": "Delete", "matrix": [2, 15], "x": 15.25, "y": 3.75},
                {"label": "End", "matrix": [2, 16], "x": 16.25, "y": 3.75},
                {"label": "Page Down", "matrix": [2, 17], "x": 17.25, "y": 3.75},

                {"label": "Caps Lock", "matrix": [3, 0], "x": 0, "y": 4.75, "w": 1.75},
                {"label": "A", "matrix": [3, 1], "x": 1.75, "y": 4.75},
                {"label": "S", "matrix": [3, 2], "x": 2.75, "y": 4.75},
                {"label": "D", "matrix": [3, 3], "x": 3.75, "y": 4.75},
                {"label": "F", "matrix": [3, 4], "x": 4.75, "y": 4.75},
                {"label": "G", "matrix": [3, 5], "x": 5.75, "y": 4.75},
                {"label": "H", "matrix": [3, 6], "x": 6.75, "y": 4.75},
                {"label": "J", "matrix": [3, 7], "x": 7.75, "y": 4.75},
                {"label": "K", "matrix": [3, 8], "x": 8.75, "y": 4.75},
                {"label": "L", "matrix": [3, 9], "x": 9.75, "y": 4.75},
                {"label": ";", "matrix": [3, 10], "x": 10.75, "y": 4.75},
                {"label": "'", "matrix": [3, 11], "x": 11.75, "y": 4.75},
                {"label": "Enter", "matrix": [3, 13], "x": 12.75, "y": 4.75, "w": 2.25},

                {"label": "Shift", "matrix": [4, 0], "x": 0, "y": 5.75, "w": 2.25},
                {"label": "Z", "matrix": [4, 2], "x": 2.25, "y": 5.75},
                {"label": "X", "matrix": [4, 3], "x": 3.25, "y": 5.75},
                {"label": "C", "matrix": [4, 4], "x": 4.25, "y": 5.75},
                {"label": "V", "matrix": [4, 5], "x": 5.25, "y": 5.75},
                {"label": "B", "matrix": [4, 6], "x": 6.25, "y": 5.75},
                {"label": "N", "matrix": [4, 7], "x": 7.25, "y": 5.75},
                {"label": "M", "matrix": [4, 8], "x": 8.25, "y": 5.75},
                {"label": ",", "matrix": [4, 9], "x": 9.25, "y": 5.75},
                {"label": ".", "matrix": [4, 10], "x": 10.25, "y": 5.75},
                {"label": "/", "matrix": [4, 11], "x": 11.25, "y": 5.75},
                {"label": "Shift", "matrix": [4, 12], "x": 12.25, "y": 5.75, "w": 1.75},
                {"label": "Fn", "matrix": [4, 13], "x": 14, "y": 5.75},

                {"label": "\u2191", "matrix": [4, 16], "x": 16.25, "y": 5.75},

                {"label": "Ctrl", "matrix": [5, 0], "x": 0, "y": 6.75, "w": 1.5},
                {"label": "Alt", "matrix": [5, 2], "x": 2.5, "y": 6.75, "w": 1.5},
                {"label": "Space", "matrix": [5, 6], "x": 4, "y": 6.75, "w": 7},
                {"label": "Alt", "matrix": [5, 10], "x": 11, "y": 6.75, "w": 1.5},
                {"label": "Ctrl", "matrix": [5, 12], "x": 13.5, "y": 6.75, "w": 1.5},

                {"label": "\u2190", "matrix": [5, 15], "x": 15.25, "y": 6.75},
                {"label": "\u2193", "matrix": [5, 16], "x": 16.25, "y": 6.75},
                {"label": "\u2192", "matrix": [5, 17], "x": 17.25, "y": 6.75}
            ]
        },
        "LAYOUT_iso": {
            "layout": [
                {"label": "Play/Pause", "matrix": [4, 15], "x": 3, "y": 0},

                {"label": "Esc", "matrix": [0, 0], "x": 0, "y": 1.5},

                {"label": "F1", "matrix": [0, 1], "x": 2, "y": 1.5},
                {"label": "F2", "matrix": [0, 2], "x": 3, "y": 1.5},
                {"label": "F3", "matrix": [0, 3], "x": 4, "y": 1.5},
                {"label": "F4", "matrix": [0, 4], "x": 5, "y": 1.5},

                {"label": "F5", "matrix": [0, 5], "x": 6.5, "y": 1.5},
                {"label": "F6", "matrix": [0, 6], "x": 7.5, "y": 1.5},
                {"label": "F7", "matrix": [0, 7], "x": 8.5, "y": 1.5},
                {"label": "F8", "matrix": [0, 8], "x": 9.5, "y": 1.5},

                {"label": "F9", "matrix": [0, 9], "x": 11, "y": 1.5},
                {"label": "F10", "matrix": [0, 10], "x": 12, "y": 1.5},
                {"label": "F11", "matrix": [0, 11], "x": 13, "y": 1.5},
                {"label": "F12", "matrix": [0, 12], "x": 14, "y": 1.5},

                {"label": "`", "matrix": [1, 0], "x": 0, "y": 2.75},
                {"label": "1", "matrix": [1, 1], "x": 1, "y": 2.75},
                {"label": "2", "matrix": [1, 2], "x": 2, "y": 2.75},
                {"label": "3", "matrix": [1, 3], "x": 3, "y": 2.75},
                {"label": "4", "matrix": [1, 4], "x": 4, "y": 2.75},
                {"label": "5", "matrix": [1, 5], "x": 5, "y": 2.75},
                {"label": "6", "matrix": [1, 6], "x": 6, "y": 2.75},
                {"label": "7", "matrix": [1, 7], "x": 7, "y": 2.75},
                {"label": "8", "matrix": [1, 8], "x": 8, "y": 2.75},
                {"label": "9", "matrix": [1, 9], "x": 9, "y": 2.75},
                {"label": "0", "matrix": [1, 10], "x": 10, "y": 2.75},
                {"label": "-", "matrix": [1, 11], "x": 11, "y": 2.75},
                {"label": "=", "matrix": [1, 12], "x": 12, "y": 2.75},
                {"label": "Backspace", "matrix": [1, 14], "x": 13, "y": 2.75, "w": 2},

                {"label": "Insert", "matrix": [1, 15], "x": 15.25, "y": 2.75},
                {"label": "Home", "matrix": [1, 16], "x": 16.25, "y": 2.75},
                {"label": "Page Up", "matrix": [1, 17], "x": 17.25, "y": 2.75},

                {"label": "Tab", "matrix": [2, 0], "x": 0, "y": 3.75, "w": 1.5},
                {"label": "Q", "matrix": [2, 1], "x": 1.5, "y": 3.75},
                {"label": "W", "matrix": [2, 2], "x": 2.5, "y": 3.75},
                {"label": "E", "matrix": [2, 3], "x": 3.5, "y": 3.75},
                {"label": "R", "matrix": [2, 4], "x": 4.5, "y": 3.75},
                {"label": "T", "matrix": [2, 5], "x": 5.5, "y": 3.75},
                {"label": "Y", "matrix": [2, 6], "x": 6.5, "y": 3.75},
                {"label": "U", "matrix": [2, 7], "x": 7.5, "y": 3.75},
                {"label": "I", "matrix": [2, 8], "x": 8.5, "y": 3.75},
                {"label": "O", "matrix": [2, 9], "x": 9.5, "y": 3.75},
                {"label": "P", "matrix": [2, 10], "x": 10.5, "y": 3.75},
                {"label": "[", "matrix": [2, 11], "x": 11.5, "y": 3.75},
                {"label": "]", "matrix": [2, 12], "x": 12.5, "y": 3.75},

                {"label": "Delete", "matrix": [2, 15], "x": 15.25, "y": 3.75},
                {"label": "End", "matrix": [2, 16], "x": 16.25, "y": 3.75},
                {"label": "Page Down", "matrix": [2, 17], "x": 17.25, "y": 3.75},

                {"label": "Caps Lock", "matrix": [3, 0], "x": 0, "y": 4.75, "w": 1.75},
                {"label": "A", "matrix": [3, 1], "x": 1.75, "y": 4.75},
                {"label": "S", "matrix": [3, 2], "x": 2.75, "y": 4.75},
                {"label": "D", "matrix": [3, 3], "x": 3.75, "y": 4.75},
                {"label": "F", "matrix": [3, 4], "x": 4.75, "y": 4.75},
                {"label": "G", "matrix": [3, 5], "x": 5.75, "y": 4.75},
                {"label": "H", "matrix": [3, 6], "x": 6.75, "y": 4.75},
                {"label": "J", "matrix": [3, 7], "x": 7.75, "y": 4.75},
                {"label": "K", "matrix": [3, 8], "x": 8.75, "y": 4.75},
                {"label": "L", "matrix": [3, 9], "x": 9.75, "y": 4.75},
                {"label": ";", "matrix": [3, 10], "x": 10.75, "y": 4.75},
                {"label": "'", "matrix": [3, 11], "x": 11.75, "y": 4.75},
                {"label": "#", "matrix": [3, 12], "x": 12.75, "y": 4.75},
                {"label": "Enter", "matrix": [3, 13], "x": 13.75, "y": 3.75, "w": 1.25, "h": 2},

                {"label": "Shift", "matrix": [4, 0], "x": 0, "y": 5.75, "w": 1.25},
                {"label": "\\", "matrix": [4, 1], "x": 1.25, "y": 5.75},
                {"label": "Z", "matrix": [4, 2], "x": 2.25, "y": 5.75},
                {"label": "X", "matrix": [4, 3], "x": 3.25, "y": 5.75},
                {"label": "C", "matrix": [4, 4], "x": 4.25, "y": 5.75},
                {"label": "V", "matrix": [4, 5], "x": 5.25, "y": 5.75},
                {"label": "B", "matrix": [4, 6], "x": 6.25, "y": 5.75},
                {"label": "N", "matrix": [4, 7], "x": 7.25, "y": 5.75},
                {"label": "M", "matrix": [4, 8], "x": 8.25, "y": 5.75},
                {"label": ",", "matrix": [4, 9], "x": 9.25, "y": 5.75},
                {"label": ".", "matrix": [4, 10], "x": 10.25, "y": 5.75},
                {"label": "/", "matrix": [4, 11], "x": 11.25, "y": 5.75},
                {"label": "Shift", "matrix": [4, 12], "x": 12.25, "y": 5.75, "w": 2.75},

                {"label": "\u2191", "matrix": [4, 16], "x": 16.25, "y": 5.75},

                {"label": "Ctrl", "matrix": [5, 0], "x": 0, "y": 6.75, "w": 1.25},
                {"label": "GUI", "matrix": [5, 1], "x": 1.25, "y": 6.75, "w": 1.25},
                {"label": "Alt", "matrix": [5, 2], "x": 2.5, "y": 6.75, "w": 1.25},
                {"label": "Space", "matrix": [5, 6], "x": 3.75, "y": 6.75, "w": 6.25},
                {"label": "Alt", "matrix": [5, 9], "x": 10, "y": 6.75, "w": 1.25},
                {"label": "GUI", "matrix": [5, 10], "x": 11.25, "y": 6.75, "w": 1.25},
                {"label": "Fn", "matrix": [5, 11], "x": 12.5, "y": 6.75, "w": 1.25},
                {"label": "Ctrl", "matrix": [5, 12], "x": 13.75, "y": 6.75, "w": 1.25},

                {"label": "\u2190", "matrix": [5, 15], "x": 15.25, "y": 6.75},
                {"label": "\u2193", "matrix": [5, 16], "x": 16.25, "y": 6.75},
                {"label": "\u2192", "matrix": [5, 17], "x": 17.25, "y": 6.75}
            ]
        },
        "LAYOUT_iso_split_bs_rshift": {
            "layout": [
                {"label": "Play/Pause", "matrix": [4, 15], "x": 3, "y": 0},

                {"label": "Esc", "matrix": [0, 0], "x": 0, "y": 1.5},

                {"label": "F1", "matrix": [0, 1], "x": 2, "y": 1.5},
                {"label": "F2", "matrix": [0, 2], "x": 3, "y": 1.5},
                {"label": "F3", "matrix": [0, 3], "x": 4, "y": 1.5},
                {"label": "F4", "matrix": [0, 4], "x": 5, "y": 1.5},

                {"label": "F5", "matrix": [0, 5], "x": 6.5, "y": 1.5},
                {"label": "F6", "matrix": [0, 6], "x": 7.5, "y": 1.5},
                {"label": "F7", "matrix": [0, 7], "x": 8.5, "y": 1.5},
                {"label": "F8", "matrix": [0, 8], "x": 9.5, "y": 1.5},

                {"label": "F9", "matrix": [0, 9], "x": 11, "y": 1.5},
                {"label": "F10", "matrix": [0, 10], "x": 12, "y": 1.5},
                {"label": "F11", "matrix": [0, 11], "x": 13, "y": 1.5},
                {"label": "F12", "matrix": [0, 12], "x": 14, "y": 1.5},

                {"label": "`", "matrix": [1, 0], "x": 0, "y": 2.75},
                {"label": "1", "matrix": [1, 1], "x": 1, "y": 2.75},
                {"label": "2", "matrix": [1, 2], "x": 2, "y": 2.75},
                {"label": "3", "matrix": [1, 3], "x": 3, "y": 2.75},
                {"label": "4", "matrix": [1, 4], "x": 4, "y": 2.75},
                {"label": "5", "matrix": [1, 5], "x": 5, "y": 2.75},
                {"label": "6", "matrix": [1, 6], "x": 6, "y": 2.75},
                {"label": "7", "matrix": [1, 7], "x": 7, "y": 2.75},
                {"label": "8", "matrix": [1, 8], "x": 8, "y": 2.75},
                {"label": "9", "matrix": [1, 9], "x": 9, "y": 2.75},
                {"label": "0", "matrix": [1, 10], "x": 10, "y": 2.75},
                {"label": "-", "matrix": [1, 11], "x": 11, "y": 2.75},
                {"label": "=", "matrix": [1, 12], "x": 12, "y": 2.75},
                {"label": "Delete", "matrix": [1, 13], "x": 13, "y": 2.75},
                {"label": "Backspace", "matrix": [1, 14], "x": 14, "y": 2.75},

                {"label": "Insert", "matrix": [1, 15], "x": 15.25, "y": 2.75},
                {"label": "Home", "matrix": [1, 16], "x": 16.25, "y": 2.75},
                {"label": "Page Up", "matrix": [1, 17], "x": 17.25, "y": 2.75},

                {"label": "Tab", "matrix": [2, 0], "x": 0, "y": 3.75, "w": 1.5},
                {"label": "Q", "matrix": [2, 1], "x": 1.5, "y": 3.75},
                {"label": "W", "matrix": [2, 2], "x": 2.5, "y": 3.75},
                {"label": "E", "matrix": [2, 3], "x": 3.5, "y": 3.75},
                {"label": "R", "matrix": [2, 4], "x": 4.5, "y": 3.75},
                {"label": "T", "matrix": [2, 5], "x": 5.5, "y": 3.75},
                {"label": "Y", "matrix": [2, 6], "x": 6.5, "y": 3.75},
                {"label": "U", "matrix": [2, 7], "x": 7.5, "y": 3.75},
                {"label": "I", "matrix": [2, 8], "x": 8.5, "y": 3.75},
                {"label": "O", "matrix": [2, 9], "x": 9.5, "y": 3.75},
                {"label": "P", "matrix": [2, 10], "x": 10.5, "y": 3.75},
                {"label": "[", "matrix": [2, 11], "x": 11.5, "y": 3.75},
                {"label": "]", "matrix": [2, 12], "x": 12.5, "y": 3.75},

                {"label": "Delete", "matrix": [2, 15], "x": 15.25, "y": 3.75},
                {"label": "End", "matrix": [2, 16], "x": 16.25, "y": 3.75},
                {"label": "Page Down", "matrix": [2, 17], "x": 17.25, "y": 3.75},

                {"label": "Caps Lock", "matrix": [3, 0], "x": 0, "y": 4.75, "w": 1.75},
                {"label": "A", "matrix": [3, 1], "x": 1.75, "y": 4.75},
                {"label": "S", "matrix": [3, 2], "x": 2.75, "y": 4.75},
                {"label": "D", "matrix": [3, 3], "x": 3.75, "y": 4.75},
                {"label": "F", "matrix": [3, 4], "x": 4.75, "y": 4.75},
                {"label": "G", "matrix": [3, 5], "x": 5.75, "y": 4.75},
                {"label": "H", "matrix": [3, 6], "x": 6.75, "y": 4.75},
                {"label": "J", "matrix": [3, 7], "x": 7.75, "y": 4.75},
                {"label": "K", "matrix": [3, 8], "x": 8.75, "y": 4.75},
                {"label": "L", "matrix": [3, 9], "x": 9.75, "y": 4.75},
                {"label": ";", "matrix": [3, 10], "x": 10.75, "y": 4.75},
                {"label": "'", "matrix": [3, 11], "x": 11.75, "y": 4.75},
                {"label": "#", "matrix": [3, 12], "x": 12.75, "y": 4.75},
                {"label": "Enter", "matrix": [3, 13], "x": 13.75, "y": 3.75, "w": 1.25, "h": 2},

                {"label": "Shift", "matrix": [4, 0], "x": 0, "y": 5.75, "w": 1.25},
                {"label": "\\", "matrix": [4, 1], "x": 1.25, "y": 5.75},
                {"label": "Z", "matrix": [4, 2], "x": 2.25, "y": 5.75},
                {"label": "X", "matrix": [4, 3], "x": 3.25, "y": 5.75},
                {"label": "C", "matrix": [4, 4], "x": 4.25, "y": 5.75},
                {"label": "V", "matrix": [4, 5], "x": 5.25, "y": 5.75},
                {"label": "B", "matrix": [4, 6], "x": 6.25, "y": 5.75},
                {"label": "N", "matrix": [4, 7], "x": 7.25, "y": 5.75},
                {"label": "M", "matrix": [4, 8], "x": 8.25, "y": 5.75},
                {"label": ",", "matrix": [4, 9], "x": 9.25, "y": 5.75},
                {"label": ".", "matrix": [4, 10], "x": 10.25, "y": 5.75},
                {"label": "/", "matrix": [4, 11], "x": 11.25, "y": 5.75},
                {"label": "Shift", "matrix": [4, 12], "x": 12.25, "y": 5.75, "w": 1.75},
                {"label": "Fn", "matrix": [4, 13], "x": 14, "y": 5.75},

                {"label": "\u2191", "matrix": [4, 16], "x": 16.25, "y": 5.75},

                {"label": "Ctrl", "matrix": [5, 0], "x": 0, "y": 6.75, "w": 1.25},
                {"label": "GUI", "matrix": [5, 1], "x": 1.25, "y": 6.75, "w": 1.25},
                {"label": "Alt", "matrix": [5, 2], "x": 2.5, "y": 6.75, "w": 1.25},
                {"label": "Space", "matrix": [5, 6], "x": 3.75, "y": 6.75, "w": 6.25},
                {"label": "Alt", "matrix": [5, 9], "x": 10, "y": 6.75, "w": 1.25},
                {"label": "GUI", "matrix": [5, 10], "x": 11.25, "y": 6.75, "w": 1.25},
                {"label": "Fn", "matrix": [5, 11], "x": 12.5, "y": 6.75, "w": 1.25},
                {"label": "Ctrl", "matrix": [5, 12], "x": 13.75, "y": 6.75, "w": 1.25},

                {"label": "\u2190", "matrix": [5, 15], "x": 15.25, "y": 6.75},
                {"label": "\u2193", "matrix": [5, 16], "x": 16.25, "y": 6.75},
                {"label": "\u2192", "matrix": [5, 17], "x": 17.25, "y": 6.75}
            ]
        },
        "LAYOUT_iso_tsangan": {
            "layout": [
                {"label": "Play/Pause", "matrix": [4, 15], "x": 3, "y": 0},

                {"label": "Esc", "matrix": [0, 0], "x": 0, "y": 1.5},

                {"label": "F1", "matrix": [0, 1], "x": 2, "y": 1.5},
                {"label": "F2", "matrix": [0, 2], "x": 3, "y": 1.5},
                {"label": "F3", "matrix": [0, 3], "x": 4, "y": 1.5},
                {"label": "F4", "matrix": [0, 4], "x": 5, "y": 1.5},

                {"label": "F5", "matrix": [0, 5], "x": 6.5, "y": 1.5},
                {"label": "F6", "matrix": [0, 6], "x": 7.5, "y": 1.5},
                {"label": "F7", "matrix": [0, 7], "x": 8.5, "y": 1.5},
                {"label": "F8", "matrix": [0, 8], "x": 9.5, "y": 1.5},

                {"label": "F9", "matrix": [0, 9], "x": 11, "y": 1.5},
                {"label": "F10", "matrix": [0, 10], "x": 12, "y": 1.5},
                {"label": "F11", "matrix": [0, 11], "x": 13, "y": 1.5},
                {"label": "F12", "matrix": [0, 12], "x": 14, "y": 1.5},

                {"label": "`", "matrix": [1, 0], "x": 0, "y": 2.75},
                {"label": "1", "matrix": [1, 1], "x": 1, "y": 2.75},
                {"label": "2", "matrix": [1, 2], "x": 2, "y": 2.75},
                {"label": "3", "matrix": [1, 3], "x": 3, "y": 2.75},
                {"label": "4", "matrix": [1, 4], "x": 4, "y": 2.75},
                {"label": "5", "matrix": [1, 5], "x": 5, "y": 2.75},
                {"label": "6", "matrix": [1, 6], "x": 6, "y": 2.75},
                {"label": "7", "matrix": [1, 7], "x": 7, "y": 2.75},
                {"label": "8", "matrix": [1, 8], "x": 8, "y": 2.75},
                {"label": "9", "matrix": [1, 9], "x": 9, "y": 2.75},
                {"label": "0", "matrix": [1, 10], "x": 10, "y": 2.75},
                {"label": "-", "matrix": [1, 11], "x": 11, "y": 2.75},
                {"label": "=", "matrix": [1, 12], "x": 12, "y": 2.75},
                {"label": "Backspace", "matrix": [1, 14], "x": 13, "y": 2.75, "w": 2},

                {"label": "Insert", "matrix": [1, 15], "x": 15.25, "y": 2.75},
                {"label": "Home", "matrix": [1, 16], "x": 16.25, "y": 2.75},
                {"label": "Page Up", "matrix": [1, 17], "x": 17.25, "y": 2.75},

                {"label": "Tab", "matrix": [2, 0], "x": 0, "y": 3.75, "w": 1.5},
                {"label": "Q", "matrix": [2, 1], "x": 1.5, "y": 3.75},
                {"label": "W", "matrix": [2, 2], "x": 2.5, "y": 3.75},
                {"label": "E", "matrix": [2, 3], "x": 3.5, "y": 3.75},
                {"label": "R", "matrix": [2, 4], "x": 4.5, "y": 3.75},
                {"label": "T", "matrix": [2, 5], "x": 5.5, "y": 3.75},
                {"label": "Y", "matrix": [2, 6], "x": 6.5, "y": 3.75},
                {"label": "U", "matrix": [2, 7], "x": 7.5, "y": 3.75},
                {"label": "I", "matrix": [2, 8], "x": 8.5, "y": 3.75},
                {"label": "O", "matrix": [2, 9], "x": 9.5, "y": 3.75},
                {"label": "P", "matrix": [2, 10], "x": 10.5, "y": 3.75},
                {"label": "[", "matrix": [2, 11], "x": 11.5, "y": 3.75},
                {"label": "]", "matrix": [2, 12], "x": 12.5, "y": 3.75},

                {"label": "Delete", "matrix": [2, 15], "x": 15.25, "y": 3.75},
                {"label": "End", "matrix": [2, 16], "x": 16.25, "y": 3.75},
                {"label": "Page Down", "matrix": [2, 17], "x": 17.25, "y": 3.75},

                {"label": "Caps Lock", "matrix": [3, 0], "x": 0, "y": 4.75, "w": 1.75},
                {"label": "A", "matrix": [3, 1], "x": 1.75, "y": 4.75},
                {"label": "S", "matrix": [3, 2], "x": 2.75, "y": 4.75},
                {"label": "D", "matrix": [3, 3], "x": 3.75, "y": 4.75},
                {"label": "F", "matrix": [3, 4], "x": 4.75, "y": 4.75},
                {"label": "G", "matrix": [3, 5], "x": 5.75, "y": 4.75},
                {"label": "H", "matrix": [3, 6], "x": 6.75, "y": 4.75},
                {"label": "J", "matrix": [3, 7], "x": 7.75, "y": 4.75},
                {"label": "K", "matrix": [3, 8], "x": 8.75, "y": 4.75},
                {"label": "L", "matrix": [3, 9], "x": 9.75, "y": 4.75},
                {"label": ";", "matrix": [3, 10], "x": 10.75, "y": 4.75},
                {"label": "'", "matrix": [3, 11], "x": 11.75, "y": 4.75},
                {"label": "#", "matrix": [3, 12], "x": 12.75, "y": 4.75},
                {"label": "Enter", "matrix": [3, 13], "x": 13.75, "y": 3.75, "w": 1.25, "h": 2},

                {"label": "Shift", "matrix": [4, 0], "x": 0, "y": 5.75, "w": 1.25},
                {"label": "\\", "matrix": [4, 1], "x": 1.25, "y": 5.75},
                {"label": "Z", "matrix": [4, 2], "x": 2.25, "y": 5.75},
                {"label": "X", "matrix": [4, 3], "x": 3.25, "y": 5.75},
                {"label": "C", "matrix": [4, 4], "x": 4.25, "y": 5.75},
                {"label": "V", "matrix": [4, 5], "x": 5.25, "y": 5.75},
                {"label": "B", "matrix": [4, 6], "x": 6.25, "y": 5.75},
                {"label": "N", "matrix": [4, 7], "x": 7.25, "y": 5.75},
                {"label": "M", "matrix": [4, 8], "x": 8.25, "y": 5.75},
                {"label": ",", "matrix": [4, 9], "x": 9.25, "y": 5.75},
                {"label": ".", "matrix": [4, 10], "x": 10.25, "y": 5.75},
                {"label": "/", "matrix": [4, 11], "x": 11.25, "y": 5.75},
                {"label": "Shift", "matrix": [4, 12], "x": 12.25, "y": 5.75, "w": 2.75},

                {"label": "\u2191", "matrix": [4, 16], "x": 16.25, "y": 5.75},

                {"label": "Ctrl", "matrix": [5, 0], "x": 0, "y": 6.75, "w": 1.5},
                {"label": "GUI", "matrix": [5, 1], "x": 1.5, "y": 6.75},
                {"label": "Alt", "matrix": [5, 2], "x": 2.5, "y": 6.75, "w": 1.5},
                {"label": "Space", "matrix": [5, 6], "x": 4, "y": 6.75, "w": 7},
                {"label": "Alt", "matrix": [5, 10], "x": 11, "y": 6.75, "w": 1.5},
                {"label": "Fn", "matrix": [5, 11], "x": 12.5, "y": 6.75},
                {"label": "Ctrl", "matrix": [5, 12], "x": 13.5, "y": 6.75, "w": 1.5},

                {"label": "\u2190", "matrix": [5, 15], "x": 15.25, "y": 6.75},
                {"label": "\u2193", "matrix": [5, 16], "x": 16.25, "y": 6.75},
                {"label": "\u2192", "matrix": [5, 17], "x": 17.25, "y": 6.75}
            ]
        },
        "LAYOUT_iso_tsangan_split_bs_rshift": {
            "layout": [
                {"label": "Play/Pause", "matrix": [4, 15], "x": 3, "y": 0},

                {"label": "Esc", "matrix": [0, 0], "x": 0, "y": 1.5},

                {"label": "F1", "matrix": [0, 1], "x": 2, "y": 1.5},
                {"label": "F2", "matrix": [0, 2], "x": 3, "y": 1.5},
                {"label": "F3", "matrix": [0, 3], "x": 4, "y": 1.5},
                {"label": "F4", "matrix": [0, 4], "x": 5, "y": 1.5},

                {"label": "F5", "matrix": [0, 5], "x": 6.5, "y": 1.5},
                {"label": "F6", "matrix": [0, 6], "x": 7.5, "y": 1.5},
                {"label": "F7", "matrix": [0, 7], "x": 8.5, "y": 1.5},
                {"label": "F8", "matrix": [0, 8], "x": 9.5, "y": 1.5},

                {"label": "F9", "matrix": [0, 9], "x": 11, "y": 1.5},
                {"label": "F10", "matrix": [0, 10], "x": 12, "y": 1.5},
                {"label": "F11", "matrix": [0, 11], "x": 13, "y": 1.5},
                {"label": "F12", "matrix": [0, 12], "x": 14, "y": 1.5},

                {"label": "`", "matrix": [1, 0], "x": 0, "y": 2.75},
                {"label": "1", "matrix": [1, 1], "x": 1, "y": 2.75},
                {"label": "2", "matrix": [1, 2], "x": 2, "y": 2.75},
                {"label": "3", "matrix": [1, 3], "x": 3, "y": 2.75},
                {"label": "4", "matrix": [1, 4], "x": 4, "y": 2.75},
                {"label": "5", "matrix": [1, 5], "x": 5, "y": 2.75},
                {"label": "6", "matrix": [1, 6], "x": 6, "y": 2.75},
                {"label": "7", "matrix": [1, 7], "x": 7, "y": 2.75},
                {"label": "8", "matrix": [1, 8], "x": 8, "y": 2.75},
                {"label": "9", "matrix": [1, 9], "x": 9, "y": 2.75},
                {"label": "0", "matrix": [1, 10], "x": 10, "y": 2.75},
                {"label": "-", "matrix": [1, 11], "x": 11, "y": 2.75},
                {"label": "=", "matrix": [1, 12], "x": 12, "y": 2.75},
                {"label": "Delete", "matrix": [1, 13], "x": 13, "y": 2.75},
                {"label": "Backspace", "matrix": [1, 14], "x": 14, "y": 2.75},

                {"label": "Insert", "matrix": [1, 15], "x": 15.25, "y": 2.75},
                {"label": "Home", "matrix": [1, 16], "x": 16.25, "y": 2.75},
                {"label": "Page Up", "matrix": [1, 17], "x": 17.25, "y": 2.75},

                {"label": "Tab", "matrix": [2, 0], "x": 0, "y": 3.75, "w": 1.5},
                {"label": "Q", "matrix": [2, 1], "x": 1.5, "y": 3.75},
                {"label": "W", "matrix": [2, 2], "x": 2.5, "y": 3.75},
                {"label": "E", "matrix": [2, 3], "x": 3.5, "y": 3.75},
                {"label": "R", "matrix": [2, 4], "x": 4.5, "y": 3.75},
                {"label": "T", "matrix": [2, 5], "x": 5.5, "y": 3.75},
                {"label": "Y", "matrix": [2, 6], "x": 6.5, "y": 3.75},
                {"label": "U", "matrix": [2, 7], "x": 7.5, "y": 3.75},
                {"label": "I", "matrix": [2, 8], "x": 8.5, "y": 3.75},
                {"label": "O", "matrix": [2, 9], "x": 9.5, "y": 3.75},
                {"label": "P", "matrix": [2, 10], "x": 10.5, "y": 3.75},
                {"label": "[", "matrix": [2, 11], "x": 11.5, "y": 3.75},
                {"label": "]", "matrix": [2, 12], "x": 12.5, "y": 3.75},

                {"label": "Delete", "matrix": [2, 15], "x": 15.25, "y": 3.75},
                {"label": "End", "matrix": [2, 16], "x": 16.25, "y": 3.75},
                {"label": "Page Down", "matrix": [2, 17], "x": 17.25, "y": 3.75},

                {"label": "Caps Lock", "matrix": [3, 0], "x": 0, "y": 4.75, "w": 1.75},
                {"label": "A", "matrix": [3, 1], "x": 1.75, "y": 4.75},
                {"label": "S", "matrix": [3, 2], "x": 2.75, "y": 4.75},
                {"label": "D", "matrix": [3, 3], "x": 3.75, "y": 4.75},
                {"label": "F", "matrix": [3, 4], "x": 4.75, "y": 4.75},
                {"label": "G", "matrix": [3, 5], "x": 5.75, "y": 4.75},
                {"label": "H", "matrix": [3, 6], "x": 6.75, "y": 4.75},
                {"label": "J", "matrix": [3, 7], "x": 7.75, "y": 4.75},
                {"label": "K", "matrix": [3, 8], "x": 8.75, "y": 4.75},
                {"label": "L", "matrix": [3, 9], "x": 9.75, "y": 4.75},
                {"label": ";", "matrix": [3, 10], "x": 10.75, "y": 4.75},
                {"label": "'", "matrix": [3, 11], "x": 11.75, "y": 4.75},
                {"label": "#", "matrix": [3, 12], "x": 12.75, "y": 4.75},
                {"label": "Enter", "matrix": [3, 13], "x": 13.75, "y": 3.75, "w": 1.25, "h": 2},

                {"label": "Shift", "matrix": [4, 0], "x": 0, "y": 5.75, "w": 1.25},
                {"label": "\\", "matrix": [4, 1], "x": 1.25, "y": 5.75},
                {"label": "Z", "matrix": [4, 2], "x": 2.25, "y": 5.75},
                {"label": "X", "matrix": [4, 3], "x": 3.25, "y": 5.75},
                {"label": "C", "matrix": [4, 4], "x": 4.25, "y": 5.75},
                {"label": "V", "matrix": [4, 5], "x": 5.25, "y": 5.75},
                {"label": "B", "matrix": [4, 6], "x": 6.25, "y": 5.75},
                {"label": "N", "matrix": [4, 7], "x": 7.25, "y": 5.75},
                {"label": "M", "matrix": [4, 8], "x": 8.25, "y": 5.75},
                {"label": ",", "matrix": [4, 9], "x": 9.25, "y": 5.75},
                {"label": ".", "matrix": [4, 10], "x": 10.25, "y": 5.75},
                {"label": "/", "matrix": [4, 11], "x": 11.25, "y": 5.75},
                {"label": "Shift", "matrix": [4, 12], "x": 12.25, "y": 5.75, "w": 1.75},
                {"label": "Fn", "matrix": [4, 13], "x": 14, "y": 5.75},

                {"label": "\u2191", "matrix": [4, 16], "x": 16.25, "y": 5.75},

                {"label": "Ctrl", "matrix": [5, 0], "x": 0, "y": 6.75, "w": 1.5},
                {"label": "GUI", "matrix": [5, 1], "x": 1.5, "y": 6.75},
                {"label": "Alt", "matrix": [5, 2], "x": 2.5, "y": 6.75, "w": 1.5},
                {"label": "Space", "matrix": [5, 6], "x": 4, "y": 6.75, "w": 7},
                {"label": "Alt", "matrix": [5, 10], "x": 11, "y": 6.75, "w": 1.5},
                {"label": "Fn", "matrix": [5, 11], "x": 12.5, "y": 6.75},
                {"label": "Ctrl", "matrix": [5, 12], "x": 13.5, "y": 6.75, "w": 1.5},

                {"label": "\u2190", "matrix": [5, 15], "x": 15.25, "y": 6.75},
                {"label": "\u2193", "matrix": [5, 16], "x": 16.25, "y": 6.75},
                {"label": "\u2192", "matrix": [5, 17], "x": 17.25, "y": 6.75}
            ]
        },
        "LAYOUT_iso_wkl": {
            "layout": [
                {"label": "Play/Pause", "matrix": [4, 15], "x": 3, "y": 0},

                {"label": "Esc", "matrix": [0, 0], "x": 0, "y": 1.5},

                {"label": "F1", "matrix": [0, 1], "x": 2, "y": 1.5},
                {"label": "F2", "matrix": [0, 2], "x": 3, "y": 1.5},
                {"label": "F3", "matrix": [0, 3], "x": 4, "y": 1.5},
                {"label": "F4", "matrix": [0, 4], "x": 5, "y": 1.5},

                {"label": "F5", "matrix": [0, 5], "x": 6.5, "y": 1.5},
                {"label": "F6", "matrix": [0, 6], "x": 7.5, "y": 1.5},
                {"label": "F7", "matrix": [0, 7], "x": 8.5, "y": 1.5},
                {"label": "F8", "matrix": [0, 8], "x": 9.5, "y": 1.5},

                {"label": "F9", "matrix": [0, 9], "x": 11, "y": 1.5},
                {"label": "F10", "matrix": [0, 10], "x": 12, "y": 1.5},
                {"label": "F11", "matrix": [0, 11], "x": 13, "y": 1.5},
                {"label": "F12", "matrix": [0, 12], "x": 14, "y": 1.5},

                {"label": "`", "matrix": [1, 0], "x": 0, "y": 2.75},
                {"label": "1", "matrix": [1, 1], "x": 1, "y": 2.75},
                {"label": "2", "matrix": [1, 2], "x": 2, "y": 2.75},
                {"label": "3", "matrix": [1, 3], "x": 3, "y": 2.75},
                {"label": "4", "matrix": [1, 4], "x": 4, "y": 2.75},
                {"label": "5", "matrix": [1, 5], "x": 5, "y": 2.75},
                {"label": "6", "matrix": [1, 6], "x": 6, "y": 2.75},
                {"label": "7", "matrix": [1, 7], "x": 7, "y": 2.75},
                {"label": "8", "matrix": [1, 8], "x": 8, "y": 2.75},
                {"label": "9", "matrix": [1, 9], "x": 9, "y": 2.75},
                {"label": "0", "matrix": [1, 10], "x": 10, "y": 2.75},
                {"label": "-", "matrix": [1, 11], "x": 11, "y": 2.75},
                {"label": "=", "matrix": [1, 12], "x": 12, "y": 2.75},
                {"label": "Backspace", "matrix": [1, 14], "x": 13, "y": 2.75, "w": 2},

                {"label": "Insert", "matrix": [1, 15], "x": 15.25, "y": 2.75},
                {"label": "Home", "matrix": [1, 16], "x": 16.25, "y": 2.75},
                {"label": "Page Up", "matrix": [1, 17], "x": 17.25, "y": 2.75},

                {"label": "Tab", "matrix": [2, 0], "x": 0, "y": 3.75, "w": 1.5},
                {"label": "Q", "matrix": [2, 1], "x": 1.5, "y": 3.75},
                {"label": "W", "matrix": [2, 2], "x": 2.5, "y": 3.75},
                {"label": "E", "matrix": [2, 3], "x": 3.5, "y": 3.75},
                {"label": "R", "matrix": [2, 4], "x": 4.5, "y": 3.75},
                {"label": "T", "matrix": [2, 5], "x": 5.5, "y": 3.75},
                {"label": "Y", "matrix": [2, 6], "x": 6.5, "y": 3.75},
                {"label": "U", "matrix": [2, 7], "x": 7.5, "y": 3.75},
                {"label": "I", "matrix": [2, 8], "x": 8.5, "y": 3.75},
                {"label": "O", "matrix": [2, 9], "x": 9.5, "y": 3.75},
                {"label": "P", "matrix": [2, 10], "x": 10.5, "y": 3.75},
                {"label": "[", "matrix": [2, 11], "x": 11.5, "y": 3.75},
                {"label": "]", "matrix": [2, 12], "x": 12.5, "y": 3.75},

                {"label": "Delete", "matrix": [2, 15], "x": 15.25, "y": 3.75},
                {"label": "End", "matrix": [2, 16], "x": 16.25, "y": 3.75},
                {"label": "Page Down", "matrix": [2, 17], "x": 17.25, "y": 3.75},

                {"label": "Caps Lock", "matrix": [3, 0], "x": 0, "y": 4.75, "w": 1.75},
                {"label": "A", "matrix": [3, 1], "x": 1.75, "y": 4.75},
                {"label": "S", "matrix": [3, 2], "x": 2.75, "y": 4.75},
                {"label": "D", "matrix": [3, 3], "x": 3.75, "y": 4.75},
                {"label": "F", "matrix": [3, 4], "x": 4.75, "y": 4.75},
                {"label": "G", "matrix": [3, 5], "x": 5.75, "y": 4.75},
                {"label": "H", "matrix": [3, 6], "x": 6.75, "y": 4.75},
                {"label": "J", "matrix": [3, 7], "x": 7.75, "y": 4.75},
                {"label": "K", "matrix": [3, 8], "x": 8.75, "y": 4.75},
                {"label": "L", "matrix": [3, 9], "x": 9.75, "y": 4.75},
                {"label": ";", "matrix": [3, 10], "x": 10.75, "y": 4.75},
                {"label": "'", "matrix": [3, 11], "x": 11.75, "y": 4.75},
                {"label": "#", "matrix": [3, 12], "x": 12.75, "y": 4.75},
                {"label": "Enter", "matrix": [3, 13], "x": 13.75, "y": 3.75, "w": 1.25, "h": 2},

                {"label": "Shift", "matrix": [4, 0], "x": 0, "y": 5.75, "w": 1.25},
                {"label": "\\", "matrix": [4, 1], "x": 1.25, "y": 5.75},
                {"label": "Z", "matrix": [4, 2], "x": 2.25, "y": 5.75},
                {"label": "X", "matrix": [4, 3], "x": 3.25, "y": 5.75},
                {"label": "C", "matrix": [4, 4], "x": 4.25, "y": 5.75},
                {"label": "V", "matrix": [4, 5], "x": 5.25, "y": 5.75},
                {"label": "B", "matrix": [4, 6], "x": 6.25, "y": 5.75},
                {"label": "N", "matrix": [4, 7], "x": 7.25, "y": 5.75},
                {"label": "M", "matrix": [4, 8], "x": 8.25, "y": 5.75},
                {"label": ",", "matrix": [4, 9], "x": 9.25, "y": 5.75},
                {"label": ".", "matrix": [4, 10], "x": 10.25, "y": 5.75},
                {"label": "/", "matrix": [4, 11], "x": 11.25, "y": 5.75},
                {"label": "Shift", "matrix": [4, 12], "x": 12.25, "y": 5.75, "w": 2.75},

                {"label": "\u2191", "matrix": [4, 16], "x": 16.25, "y": 5.75},

                {"label": "Ctrl", "matrix": [5, 0], "x": 0, "y": 6.75, "w": 1.5},
                {"label": "Alt", "matrix": [5, 2], "x": 2.5, "y": 6.75, "w": 1.5},
                {"label": "Space", "matrix": [5, 6], "x": 4, "y": 6.75, "w": 7},
                {"label": "Alt", "matrix": [5, 10], "x": 11, "y": 6.75, "w": 1.5},
                {"label": "Ctrl", "matrix": [5, 12], "x": 13.5, "y": 6.75, "w": 1.5},

                {"label": "\u2190", "matrix": [5, 15], "x": 15.25, "y": 6.75},
                {"label": "\u2193", "matrix": [5, 16], "x": 16.25, "y": 6.75},
                {"label": "\u2192", "matrix": [5, 17], "x": 17.25, "y": 6.75}
            ]
        },
        "LAYOUT_iso_wkl_split_bs_rshift": {
            "layout": [
                {"label": "Play/Pause", "matrix": [4, 15], "x": 3, "y": 0},

                {"label": "Esc", "matrix": [0, 0], "x": 0, "y": 1.5},

                {"label": "F1", "matrix": [0, 1], "x": 2, "y": 1.5},
                {"label": "F2", "matrix": [0, 2], "x": 3, "y": 1.5},
                {"label": "F3", "matrix": [0, 3], "x": 4, "y": 1.5},
                {"label": "F4", "matrix": [0, 4], "x": 5, "y": 1.5},

                {"label": "F5", "matrix": [0, 5], "x": 6.5, "y": 1.5},
                {"label": "F6", "matrix": [0, 6], "x": 7.5, "y": 1.5},
                {"label": "F7", "matrix": [0, 7], "x": 8.5, "y": 1.5},
                {"label": "F8", "matrix": [0, 8], "x": 9.5, "y": 1.5},

                {"label": "F9", "matrix": [0, 9], "x": 11, "y": 1.5},
                {"label": "F10", "matrix": [0, 10], "x": 12, "y": 1.5},
                {"label": "F11", "matrix": [0, 11], "x": 13, "y": 1.5},
                {"label": "F12", "matrix": [0, 12], "x": 14, "y": 1.5},

                {"label": "`", "matrix": [1, 0], "x": 0, "y": 2.75},
                {"label": "1", "matrix": [1, 1], "x": 1, "y": 2.75},
                {"label": "2", "matrix": [1, 2], "x": 2, "y": 2.75},
                {"label": "3", "matrix": [1, 3], "x": 3, "y": 2.75},
                {"label": "4", "matrix": [1, 4], "x": 4, "y": 2.75},
                {"label": "5", "matrix": [1, 5], "x": 5, "y": 2.75},
                {"label": "6", "matrix": [1, 6], "x": 6, "y": 2.75},
                {"label": "7", "matrix": [1, 7], "x": 7, "y": 2.75},
                {"label": "8", "matrix": [1, 8], "x": 8, "y": 2.75},
                {"label": "9", "matrix": [1, 9], "x": 9, "y": 2.75},
                {"label": "0", "matrix": [1, 10], "x": 10, "y": 2.75},
                {"label": "-", "matrix": [1, 11], "x": 11, "y": 2.75},
                {"label": "=", "matrix": [1, 12], "x": 12, "y": 2.75},
                {"label": "Delete", "matrix": [1, 13], "x": 13, "y": 2.75},
                {"label": "Backspace", "matrix": [1, 14], "x": 14, "y": 2.75},

                {"label": "Insert", "matrix": [1, 15], "x": 15.25, "y": 2.75},
                {"label": "Home", "matrix": [1, 16], "x": 16.25, "y": 2.75},
                {"label": "Page Up", "matrix": [1, 17], "x": 17.25, "y": 2.75},

                {"label": "Tab", "matrix": [2, 0], "x": 0, "y": 3.75, "w": 1.5},
                {"label": "Q", "matrix": [2, 1], "x": 1.5, "y": 3.75},
                {"label": "W", "matrix": [2, 2], "x": 2.5, "y": 3.75},
                {"label": "E", "matrix": [2, 3], "x": 3.5, "y": 3.75},
                {"label": "R", "matrix": [2, 4], "x": 4.5, "y": 3.75},
                {"label": "T", "matrix": [2, 5], "x": 5.5, "y": 3.75},
                {"label": "Y", "matrix": [2, 6], "x": 6.5, "y": 3.75},
                {"label": "U", "matrix": [2, 7], "x": 7.5, "y": 3.75},
                {"label": "I", "matrix": [2, 8], "x": 8.5, "y": 3.75},
                {"label": "O", "matrix": [2, 9], "x": 9.5, "y": 3.75},
                {"label": "P", "matrix": [2, 10], "x": 10.5, "y": 3.75},
                {"label": "[", "matrix": [2, 11], "x": 11.5, "y": 3.75},
                {"label": "]", "matrix": [2, 12], "x": 12.5, "y": 3.75},

                {"label": "Delete", "matrix": [2, 15], "x": 15.25, "y": 3.75},
                {"label": "End", "matrix": [2, 16], "x": 16.25, "y": 3.75},
                {"label": "Page Down", "matrix": [2, 17], "x": 17.25, "y": 3.75},

                {"label": "Caps Lock", "matrix": [3, 0], "x": 0, "y": 4.75, "w": 1.75},
                {"label": "A", "matrix": [3, 1], "x": 1.75, "y": 4.75},
                {"label": "S", "matrix": [3, 2], "x": 2.75, "y": 4.75},
                {"label": "D", "matrix": [3, 3], "x": 3.75, "y": 4.75},
                {"label": "F", "matrix": [3, 4], "x": 4.75, "y": 4.75},
                {"label": "G", "matrix": [3, 5], "x": 5.75, "y": 4.75},
                {"label": "H", "matrix": [3, 6], "x": 6.75, "y": 4.75},
                {"label": "J", "matrix": [3, 7], "x": 7.75, "y": 4.75},
                {"label": "K", "matrix": [3, 8], "x": 8.75, "y": 4.75},
                {"label": "L", "matrix": [3, 9], "x": 9.75, "y": 4.75},
                {"label": ";", "matrix": [3, 10], "x": 10.75, "y": 4.75},
                {"label": "'", "matrix": [3, 11], "x": 11.75, "y": 4.75},
                {"label": "#", "matrix": [3, 12], "x": 12.75, "y": 4.75},
                {"label": "Enter", "matrix": [3, 13], "x": 13.75, "y": 3.75, "w": 1.25, "h": 2},

                {"label": "Shift", "matrix": [4, 0], "x": 0, "y": 5.75, "w": 1.25},
                {"label": "\\", "matrix": [4, 1], "x": 1.25, "y": 5.75},
                {"label": "Z", "matrix": [4, 2], "x": 2.25, "y": 5.75},
                {"label": "X", "matrix": [4, 3], "x": 3.25, "y": 5.75},
                {"label": "C", "matrix": [4, 4], "x": 4.25, "y": 5.75},
                {"label": "V", "matrix": [4, 5], "x": 5.25, "y": 5.75},
                {"label": "B", "matrix": [4, 6], "x": 6.25, "y": 5.75},
                {"label": "N", "matrix": [4, 7], "x": 7.25, "y": 5.75},
                {"label": "M", "matrix": [4, 8], "x": 8.25, "y": 5.75},
                {"label": ",", "matrix": [4, 9], "x": 9.25, "y": 5.75},
                {"label": ".", "matrix": [4, 10], "x": 10.25, "y": 5.75},
                {"label": "/", "matrix": [4, 11], "x": 11.25, "y": 5.75},
                {"label": "Shift", "matrix": [4, 12], "x": 12.25, "y": 5.75, "w": 1.75},
                {"label": "Fn", "matrix": [4, 13], "x": 14, "y": 5.75},

                {"label": "\u2191", "matrix": [4, 16], "x": 16.25, "y": 5.75},

                {"label": "Ctrl", "matrix": [5, 0], "x": 0, "y": 6.75, "w": 1.5},
                {"label": "Alt", "matrix": [5, 2], "x": 2.5, "y": 6.75, "w": 1.5},
                {"label": "Space", "matrix": [5, 6], "x": 4, "y": 6.75, "w": 7},
                {"label": "Alt", "matrix": [5, 10], "x": 11, "y": 6.75, "w": 1.5},
                {"label": "Ctrl", "matrix": [5, 12], "x": 13.5, "y": 6.75, "w": 1.5},

                {"label": "\u2190", "matrix": [5, 15], "x": 15.25, "y": 6.75},
                {"label": "\u2193", "matrix": [5, 16], "x": 16.25, "y": 6.75},
                {"label": "\u2192", "matrix": [5, 17], "x": 17.25, "y": 6.75}
            ]
        }
    }
}
