{
    "manufacturer": "SIRIND",
    "keyboard_name": "ChickPad",
    "maintainer": "eerraa",
    "bootloader": "rp2040",
    "build": {
        "debounce_type": "sym_defer_pk"
    },
    "diode_direction": "COL2ROW",
    "features": {
        "bootmagic": true,
        "extrakey": true,
        "mousekey": true,
        "nkro": true,
        "rgb_matrix": true
    },
    "matrix_pins": {
        "cols": ["GP23", "GP25", "GP3", "GP5", "GP4"],
        "rows": ["GP18", "GP24", "GP22"]
    },
    "processor": "RP2040",
    "rgb_matrix": {
        "animations": {
            "alphas_mods": true,
            "band_pinwheel_sat": true,
            "band_pinwheel_val": true,
            "band_sat": true,
            "band_spiral_sat": true,
            "band_spiral_val": true,
            "band_val": true,
            "breathing": true,
            "cycle_all": true,
            "cycle_left_right": true,
            "cycle_out_in": true,
            "cycle_out_in_dual": true,
            "cycle_pinwheel": true,
            "cycle_spiral": true,
            "cycle_up_down": true,
            "digital_rain": true,
            "dual_beacon": true,
            "flower_blooming": true,
            "gradient_left_right": true,
            "gradient_up_down": true,
            "hue_breathing": true,
            "hue_pendulum": true,
            "hue_wave": true,
            "jellybean_raindrops": true,
            "multisplash": true,
            "pixel_flow": true,
            "pixel_fractal": true,
            "pixel_rain": true,
            "rainbow_beacon": true,
            "rainbow_moving_chevron": true,
            "rainbow_pinwheels": true,
            "raindrops": true,
            "riverflow": true,
            "solid_multisplash": true,
            "solid_reactive": true,
            "solid_reactive_cross": true,
            "solid_reactive_multicross": true,
            "solid_reactive_multinexus": true,
            "solid_reactive_multiwide": true,
            "solid_reactive_nexus": true,
            "solid_reactive_simple": true,
            "solid_reactive_wide": true,
            "solid_splash": true,
            "splash": true,
            "starlight": true,
            "starlight_dual_hue": true,
            "starlight_dual_sat": true,
            "typing_heatmap": true
        },
        "driver": "ws2812",
        "layout": [
            {"matrix": [0, 0], "x": 0, "y": 0, "flags": 4},
            {"matrix": [0, 1], "x": 56, "y": 0, "flags": 4},
            {"matrix": [0, 2], "x": 112, "y": 0, "flags": 4},
            {"matrix": [0, 3], "x": 168, "y": 0, "flags": 4},
            {"matrix": [0, 4], "x": 224, "y": 16, "flags": 1},
            {"matrix": [1, 3], "x": 168, "y": 32, "flags": 4},
            {"matrix": [1, 2], "x": 112, "y": 32, "flags": 4},
            {"matrix": [1, 1], "x": 56, "y": 32, "flags": 4},
            {"matrix": [1, 0], "x": 0, "y": 32, "flags": 4},
            {"matrix": [2, 0], "x": 28, "y": 64, "flags": 1},
            {"matrix": [2, 2], "x": 112, "y": 64, "flags": 4},
            {"matrix": [2, 3], "x": 168, "y": 64, "flags": 4},
            {"matrix": [2, 4], "x": 224, "y": 64, "flags": 4}
        ],
        "sleep": true
    },
    "url": "",
    "usb": {
        "device_version": "1.0.0",
        "pid": "0x0015",
        "vid": "0x4552"
    },
    "ws2812": {
        "driver": "vendor",
        "pin": "GP19"
    },
    "layouts": {
        "LAYOUT": {
            "layout": [
                {"matrix": [0, 0], "x": 0, "y": 0},
                {"matrix": [0, 1], "x": 1, "y": 0},
                {"matrix": [0, 2], "x": 2, "y": 0},
                {"matrix": [0, 3], "x": 3, "y": 0},
                {"matrix": [0, 4], "x": 4.25, "y": 0, "w": 1.25, "h": 2},
                {"matrix": [1, 0], "x": 0, "y": 1, "w": 1.25},
                {"matrix": [1, 1], "x": 1.25, "y": 1},
                {"matrix": [1, 2], "x": 2.25, "y": 1},
                {"matrix": [1, 3], "x": 3.25, "y": 1},
                {"matrix": [2, 0], "x": 0, "y": 2, "w": 2.25},
                {"matrix": [2, 2], "x": 2.25, "y": 2},
                {"matrix": [2, 3], "x": 3.25, "y": 2},
                {"matrix": [2, 4], "x": 4.25, "y": 2}
            ]
        }
    }
}
